Workbook

Sheet Сводка
A1: Отчёт: интеграционное и нагрузочное тестирование Luckfox Image Builder
A2: Дата проведения: 30.09.2026 · версия: 27e1fb0 (Add component filter and price sorting to libraries) · стенд: WSL2 Ubuntu 24.04, 16 vCPU / 7.5 ГБ, MySQL 8, JDK 17
A4: 1. Интеграционное тестирование (по этапам)
A5: Этап | B5: Всего | C5: PASS | D5: FAIL | E5: Успешно, %
A6: 1. Развёртывание | B6: =COUNTIF('Интеграционные тесты'!$C:$C,A6) -> 7 | C6: =COUNTIFS('Интеграционные тесты'!$C:$C,A6,'Интеграционные тесты'!$H:$H,"PASS") -> 5 | D6: =COUNTIFS('Интеграционные тесты'!$C:$C,A6,'Интеграционные тесты'!$H:$H,"FAIL") -> 2 | E6: =IF(B6=0,0,C6/B6) -> 0.71428571
A7: 2. Аутентификация и доступ | B7: =COUNTIF('Интеграционные тесты'!$C:$C,A7) -> 11 | C7: =COUNTIFS('Интеграционные тесты'!$C:$C,A7,'Интеграционные тесты'!$H:$H,"PASS") -> 4 | D7: =COUNTIFS('Интеграционные тесты'!$C:$C,A7,'Интеграционные тесты'!$H:$H,"FAIL") -> 7 | E7: =IF(B7=0,0,C7/B7) -> 0.36363636
A8: 3. Каталог и пагинация | B8: =COUNTIF('Интеграционные тесты'!$C:$C,A8) -> 5 | C8: =COUNTIFS('Интеграционные тесты'!$C:$C,A8,'Интеграционные тесты'!$H:$H,"PASS") -> 2 | D8: =COUNTIFS('Интеграционные тесты'!$C:$C,A8,'Интеграционные тесты'!$H:$H,"FAIL") -> 3 | E8: =IF(B8=0,0,C8/B8) -> 0.4
A9: 4. Компоненты (ADMIN) | B9: =COUNTIF('Интеграционные тесты'!$C:$C,A9) -> 5 | C9: =COUNTIFS('Интеграционные тесты'!$C:$C,A9,'Интеграционные тесты'!$H:$H,"PASS") -> 4 | D9: =COUNTIFS('Интеграционные тесты'!$C:$C,A9,'Интеграционные тесты'!$H:$H,"FAIL") -> 1 | E9: =IF(B9=0,0,C9/B9) -> 0.8
A10: 5. Заказ и сборка образа | B10: =COUNTIF('Интеграционные тесты'!$C:$C,A10) -> 12 | C10: =COUNTIFS('Интеграционные тесты'!$C:$C,A10,'Интеграционные тесты'!$H:$H,"PASS") -> 8 | D10: =COUNTIFS('Интеграционные тесты'!$C:$C,A10,'Интеграционные тесты'!$H:$H,"FAIL") -> 4 | E10: =IF(B10=0,0,C10/B10) -> 0.66666667
A11: 6. Управление пользователями | B11: =COUNTIF('Интеграционные тесты'!$C:$C,A11) -> 3 | C11: =COUNTIFS('Интеграционные тесты'!$C:$C,A11,'Интеграционные тесты'!$H:$H,"PASS") -> 2 | D11: =COUNTIFS('Интеграционные тесты'!$C:$C,A11,'Интеграционные тесты'!$H:$H,"FAIL") -> 1 | E11: =IF(B11=0,0,C11/B11) -> 0.66666667
A12: 7. Отказоустойчивость | B12: =COUNTIF('Интеграционные тесты'!$C:$C,A12) -> 4 | C12: =COUNTIFS('Интеграционные тесты'!$C:$C,A12,'Интеграционные тесты'!$H:$H,"PASS") -> 2 | D12: =COUNTIFS('Интеграционные тесты'!$C:$C,A12,'Интеграционные тесты'!$H:$H,"FAIL") -> 2 | E12: =IF(B12=0,0,C12/B12) -> 0.5
A13: 8. E2E через браузер (UI) | B13: =COUNTIF('Интеграционные тесты'!$C:$C,A13) -> 9 | C13: =COUNTIFS('Интеграционные тесты'!$C:$C,A13,'Интеграционные тесты'!$H:$H,"PASS") -> 7 | D13: =COUNTIFS('Интеграционные тесты'!$C:$C,A13,'Интеграционные тесты'!$H:$H,"FAIL") -> 2 | E13: =IF(B13=0,0,C13/B13) -> 0.77777778
A14: Итого | B14: =SUM(B6:B13) -> 56 | C14: =SUM(C6:C13) -> 34 | D14: =SUM(D6:D13) -> 22 | E14: =IF(B14=0,0,C14/B14) -> 0.60714286
A16: 2. Найденные дефекты по серьёзности
A17: Серьёзность | B17: Количество
A18: Критическая | B18: =COUNTIF(Дефекты!$B:$B,A18) -> 1
A19: Высокая | B19: =COUNTIF(Дефекты!$B:$B,A19) -> 4
A20: Средняя | B20: =COUNTIF(Дефекты!$B:$B,A20) -> 9
A21: Низкая | B21: =COUNTIF(Дефекты!$B:$B,A21) -> 8
A22: Всего | B22: =SUM(B18:B21) -> 22
A24: 3. Нагрузочное тестирование (ключевые показатели)
A25: Профиль | B25: Запросов | C25: RPS средн. | D25: Ошибки | E25: p95, мс | F25: p99, мс | G25: Критерии (SLA)
A26: L-01 Дымовой (baseline) | B26: ='Нагрузка — итоги'!D5 -> 320 | C26: ='Нагрузка — итоги'!F5 -> 5.7 | D26: ='Нагрузка — итоги'!I5 -> 0 | E26: ='Нагрузка — итоги'!N5 -> 111.47 | F26: ='Нагрузка — итоги'!O5 -> 194.49 | G26: ='Нагрузка — итоги'!AB5 -> PASS
A27: L-02 Просмотр каталогов (гости) | B27: ='Нагрузка — итоги'!D6 -> 7772 | C27: ='Нагрузка — итоги'!F6 -> 30.3 | D27: ='Нагрузка — итоги'!I6 -> 0 | E27: ='Нагрузка — итоги'!N6 -> 15.28 | F27: ='Нагрузка — итоги'!O6 -> 17.23 | G27: ='Нагрузка — итоги'!AB6 -> PASS
A28: L-03 Смешанный продакшен-профиль (целевая нагрузка) | B28: ='Нагрузка — итоги'!D7 -> 22489 | C28: ='Нагрузка — итоги'!F7 -> 60.3 | D28: ='Нагрузка — итоги'!I7 -> 0 | E28: ='Нагрузка — итоги'!N7 -> 17.52 | F28: ='Нагрузка — итоги'!O7 -> 34.41 | G28: ='Нагрузка — итоги'!AB7 -> PASS
A29: L-04 Стресс (поиск предела) | B29: ='Нагрузка — итоги'!D8 -> 176498 | C29: ='Нагрузка — итоги'!F8 -> 343.8 | D29: ='Нагрузка — итоги'!I8 -> 0 | E29: ='Нагрузка — итоги'!N8 -> 15.02 | F29: ='Нагрузка — итоги'!O8 -> 16.36 | G29: ='Нагрузка — итоги'!AB8 -> PASS
A30: L-04b Стресс до отказа (breakpoint) | B30: ='Нагрузка — итоги'!D9 -> 560700 | C30: ='Нагрузка — итоги'!F9 -> 1294.4 | D30: ='Нагрузка — итоги'!I9 -> 0 | E30: ='Нагрузка — итоги'!N9 -> 2949.46 | F30: ='Нагрузка — итоги'!O9 -> 3170.03 | G30: ='Нагрузка — итоги'!AB9 -> FAIL
A31: L-05 Всплеск (spike) | B31: ='Нагрузка — итоги'!D10 -> 55548 | C31: ='Нагрузка — итоги'!F10 -> 292.9 | D31: ='Нагрузка — итоги'!I10 -> 0 | E31: ='Нагрузка — итоги'!N10 -> 15.41 | F31: ='Нагрузка — итоги'!O10 -> 18.04 | G31: ='Нагрузка — итоги'!AB10 -> PASS
A32: L-06 Шторм авторизаций | B32: ='Нагрузка — итоги'!D11 -> 9618 | C32: ='Нагрузка — итоги'!F11 -> 42.4 | D32: ='Нагрузка — итоги'!I11 -> 0 | E32: ='Нагрузка — итоги'!N11 -> 987.93 | F32: ='Нагрузка — итоги'!O11 -> 1049.75 | G32: ='Нагрузка — итоги'!AB11 -> PASS
A33: L-07 Пакет заказов сборки (очередь) | B33: ='Нагрузка — итоги'!D12 -> 3059 | C33: ='Нагрузка — итоги'!F12 -> 16.1 | D33: ='Нагрузка — итоги'!I12 -> 0 | E33: ='Нагрузка — итоги'!N12 -> 35.72 | F33: ='Нагрузка — итоги'!O12 -> 157.34 | G33: ='Нагрузка — итоги'!AB12 -> PASS
A34: L-08 Скачивание артефактов | B34: ='Нагрузка — итоги'!D13 -> 2256 | C34: ='Нагрузка — итоги'!F13 -> 19.6 | D34: ='Нагрузка — итоги'!I13 -> 0 | E34: ='Нагрузка — итоги'!N13 -> 103.87 | F34: ='Нагрузка — итоги'!O13 -> 234.58 | G34: ='Нагрузка — итоги'!AB13 -> PASS
A35: L-09 Длительная нагрузка (soak) | B35: ='Нагрузка — итоги'!D14 -> 23230 | C35: ='Нагрузка — итоги'!F14 -> 26.4 | D35: ='Нагрузка — итоги'!I14 -> 0 | E35: ='Нагрузка — итоги'!N14 -> 18.65 | F35: ='Нагрузка — итоги'!O14 -> 73.41 | G35: ='Нагрузка — итоги'!AB14 -> PASS
A36: L-10a Объём: базовая БД | B36: ='Нагрузка — итоги'!D15 -> 8845 | C36: ='Нагрузка — итоги'!F15 -> 51.5 | D36: ='Нагрузка — итоги'!I15 -> 0 | E36: ='Нагрузка — итоги'!N15 -> 9.19 | F36: ='Нагрузка — итоги'!O15 -> 10.31 | G36: ='Нагрузка — итоги'!AB15 -> PASS
A37: L-10b Объём: БД ×100 | B37: ='Нагрузка — итоги'!D16 -> 8815 | C37: ='Нагрузка — итоги'!F16 -> 50.9 | D37: ='Нагрузка — итоги'!I16 -> 0 | E37: ='Нагрузка — итоги'!N16 -> 27.71 | F37: ='Нагрузка — итоги'!O16 -> 31.82 | G37: ='Нагрузка — итоги'!AB16 -> PASS
A39: 4. Выводы
A40: • Интеграционное тестирование: 56 тестов (47 API на прод-подобном стенде + 9 E2E в браузере). 34 прошли, 22 выявили отклонения. Основные бизнес-сценарии работают корректно: регистрация и вход, каталоги с поиском/фильтрами/сортировкой/пагинацией, защита графа зависимостей, заказ → сборка → скачивание валидного ext4-образа, администрирование, FIFO-очередь с одним воркером, оптимистичная блокировка, сохранность данных при перезапуске.
A41: • Найдено 22 дефекта: 1 критический (секрет JWT в репозитории — можно выпустить токен администратора), 4 высоких (скачивание чужих образов по id, зависание очереди после падения backend, необработанные ошибки разбора JWT, нет защиты от перебора паролей), 9 средних, 8 низких.
A42: • Системная проблема обработки ошибок безопасности: Spring Security отвечает 403 без тела там, где нужны 401/400/503 (нет entry point, /error закрыт). Из-за этого фронтенд не выкидывает на вход при истёкшем токене, а пользователь видит «Request failed with status code 403».
A43: • Нагрузка: все 12 профилей (≈879 тыс. запросов) — ни одной HTTP-ошибки. Целевой профиль 100 одновременных пользователей (≈60 запросов/с): p95 чтения 17,5 мс, записи < 60 мс, машина загружена на ≈5 %.
A44: • Предел чтения каталогов ≈1 300 запросов/с (≈20× целевой нагрузки). Выше система не отказывает, а копит запросы в очереди — медиана 2–3 с. Узкое место — БД: N+1 (≈12,5 SQL на HTTP-запрос), пул HikariCP 10 соединений.
A45: • Вход (BCrypt) — ≈50–60 входов/с на стенде; на 100/с задержка растёт в 11 раз и занимает ≈8 ядер. Ограничения частоты попыток нет — это и риск перебора паролей.
A46: • Очередь сборок под нагрузкой надёжна (FIFO, 355 сборок без потерь), но строго последовательна: при реальной сборке SDK 1–3 ч это главный ограничитель сервиса (≈8–24 образа в сутки).
A47: • Длительная нагрузка (15 мин): утечек памяти и деградации нет. Объём ×100 (20 тыс. образов): p95 вырос 9 → 28 мс, страница из 100 образов — 389 SQL-запросов; при росте данных N+1 станет главной проблемой.
A48: • Приоритет исправлений: DEF-07 → DEF-16 → DEF-19 → DEF-05/04/03 (единая обработка ошибок безопасности) → DEF-21 → DEF-12/22 (производительность БД).
A49: • Оптимизация по итогам нагрузки (лист «Оптимизация»): устранены N+1 и удержание соединения БД (Open Session In View), добавлены индексы, пул и быстрый отказ 503, защита входа от перебора. Повторный прогон тех же профилей: предел чтения 1 470 → 3 830 запросов/с (×2,6), p95 целевого профиля 17,5 → 5,6 мс, вход на 100/с p95 1 050 → 127 мс, страница из 100 образов на БД ×100 — 389 → 11 SQL. Исправлены DEF-12, DEF-20, DEF-21, DEF-22, частично DEF-23; добавлено 84 модульных теста.

Sheet Стенд и методика
A1: Тестовый стенд и методика
A3: Аппаратная платформа
A4: Процессор | B4: AMD Ryzen 7 5800HS with Radeon Graphics, 16 логических ядер (выделены WSL2)
A5: Память | B5: 7638 МБ (лимит WSL2)
A6: ОС | B6: Ubuntu 24.04 LTS в WSL2, ядро 6.6.87.2-microsoft-standard-WSL2; хост — Windows 11 Enterprise LTSC 2024
A7: Диск | B7: ext4 (виртуальный диск WSL2) на NVMe хоста
A9: Программное обеспечение
A10: JDK | B10: openjdk version "17.0.20.1" 2026-08-18
A11: Backend | B11: Spring Boot 3.2.0 (встроенный Tomcat: 200 потоков по умолчанию), Hibernate 6, HikariCP (пул 10 соединений по умолчанию), JWT (jjwt)
A12: СУБД | B12: MySQL 8.0.46-0ubuntu0.24.04.4 (параметры по умолчанию, innodb_buffer_pool_size 128 МБ)
A13: Frontend | B13: React 18 + Vite 5, prod-сборка (vite build, VITE_API_URL=http://localhost:8080/api), раздача server.mjs на Node v24.20.0
A14: Генератор нагрузки | B14: k6 v0.54.0 (Grafana k6)
A15: Интеграционные тесты | B15: Python 3.12 + requests (tests/integration/run_integration.py); E2E — Playwright (Chromium) с хоста Windows
A16: Мониторинг | B16: tests/load/monitor.py: /proc (CPU, RSS, потоки), jstat -gc (heap, GC), SHOW GLOBAL STATUS (соединения, Questions); шаг 1 с
A18: Конфигурация стенда (приближена к docker-compose)
A19: Топология | B19: 3 процесса как 3 контейнера compose: MySQL :3306 ← backend jar :8080 ← браузер/клиенты; фронтенд :5173 (server.mjs) обращается к API по абсолютному URL (CORS)
A20: JVM | B20: -Xms512m -Xmx1g -XX:+UseG1GC -Djava.net.preferIPv4Stack=true (java -jar, профиль по умолчанию)
A21: Сборка образов | B21: scripts/luckfox_build.sh в режиме симуляции (реальный ext4-образ 16+N МБ), LUCKFOX_SIM_DELAY=3 с — имитация длительности; очередь с одним воркером
A22: База данных | B22: Чистая БД, схема создаётся Hibernate (ddl-auto=update), наполнение DataSeeder: 67 компонентов, 15 образов через конвейер сборки, admin
A23: Ограничения стенда | B23: Генератор нагрузки, backend и MySQL работают на одной машине и делят CPU — абсолютные пределы занижены относительно выделенного сервера; сеть — loopback (нет сетевых задержек)
A25: Методика
A26: Интеграционное: подход | B26: Чёрный ящик по HTTP против развёрнутого стенда с реальными MySQL, файловой системой, внешним процессом сборки и CORS. Каждый тест создаёт собственные данные (уникальные email/имена). Проверяются ответы API, состояние БД (information_schema, счётчики) и артефакты на диске (ext4-магия, содержимое через debugfs).
A27: Интеграционное: этапы | B27: 1 — развёртывание (SPA, статика, CORS, схема, DataSeeder); 2 — аутентификация и доступ; 3 — каталог и пагинация; 4 — компоненты (ADMIN); 5 — заказ и сборка образа; 6 — управление пользователями; 7 — отказоустойчивость (SIGTERM/kill -9 backend во время сборки, остановка MySQL); 8 — E2E в браузере (Playwright).
A28: Интеграционное: прогон | B28: Финальный прогон — на полностью пересозданном стенде (чистая БД). Первый прогон использовался для отладки тестов: 4 ложных срабатывания (имя таблицы, порядок параллельных заказов, формулировки) исправлены в тестах, а не в ожиданиях к системе.
A29: Нагрузочное: инструмент | B29: Grafana k6: модели closed (виртуальные пользователи с паузами «на чтение») и open (заданная интенсивность, ramping/constant-arrival-rate). Операции размечены тегом name, чтение/запись — тегом kind. setup() регистрирует тестовых пользователей; эти запросы исключены из метрик.
A30: Нагрузочное: метрики | B30: Время отклика (avg/min/med/p90/p95/p99/max), RPS, доля ошибок (http_req_failed и checks), активные VU, пропущенные итерации, объём данных. Время от заказа до READY. Ресурсы с шагом 1 с: CPU и RSS процессов java и mysqld, heap и GC (jstat), потоки, соединения MySQL, число SQL-запросов (Questions).
A31: Критерии успеха (SLA) | B31: Ошибки < 1 %; p95 чтения < 500 мс; p95 записи < 1000 мс; p95 входа < 1000 мс; p95 скачивания 18 МБ < 3000 мс; для стресса — фиксация точки насыщения.
A32: Порядок прогона | B32: Профили выполнялись последовательно на одном экземпляре backend (без перезапуска, паузы 20 с). Прогрев JVM — дымовой профиль. БД росла по ходу тестов (39 → ≈550 образов); объёмный тест — в конце, на отдельно наполненной БД.
A33: Ограничения | B33: Генератор нагрузки работает на той же машине, что и система: в breakpoint машина загружена на 69–85 %, k6 упёрся в 3000 VU, так что предел ≈1 300 запросов/с — нижняя оценка. Сборка — симуляция (3 с + mkfs) вместо 1–3 ч. Сеть — loopback.
A34: Особенность стенда | B34: Backend по умолчанию слушал только IPv6-сокет, и браузер на хосте Windows не мог достучаться до API через проброс WSL (ERR_CONNECTION_REFUSED). Для стенда добавлен -Djava.net.preferIPv4Stack=true; в Docker-развёртывании проблема не проявляется.

Sheet Интеграционные тесты
A1: Интеграционные тесты (чёрный ящик по HTTP на прод-подобном стенде + E2E в браузере)
A2: Прогон c28bab, завершён 2026-09-29 23:58:59. Скрипт: tests/integration/run_integration.py; E2E: Playwright.
A4: № | B4: ID | C4: Этап | D4: Тест | E4: Описание / шаги | F4: Ожидаемый результат | G4: Фактический результат | H4: Статус | I4: Время, с | J4: Дефект
A5: 1 | B5: INT-01 | C5: 1. Развёртывание | D5: Фронтенд (prod-сборка) отдаёт SPA и ассеты | E5: GET / и JS/CSS-бандлы из dist/ через server.mjs | F5: 200, text/html; бандлы 200 с корректным Content-Type | G5: index-CTuQi8U5.js text/javascript; charset=utf-8 244 КБ; index-CYtgMNis.css text/css; charset=utf-8 8 КБ | H5: PASS | I5: 0.02
A6: 2 | B6: INT-02 | C6: 1. Развёртывание | D6: Прямой переход по клиентскому маршруту (deep link) | E6: Обновление страницы на /editor/image и /admin/users | F6: 200 и index.html (SPA fallback) | G6: /editor/image → 200, /admin/users → 200, /no/such/route → 200 | H6: PASS | I6: 0.01
A7: 3 | B7: INT-03 | C7: 1. Развёртывание | D7: Отдача несуществующего ассета | E7: GET /assets/missing.js (напр. после деплоя новой версии у клиента старый index.html) | F7: 404 для отсутствующего файла со статикой | G7: HTTP 200, Content-Type text/html; charset=utf-8 — браузер получит HTML вместо JS | H7: FAIL | I7: 0 | J7: DEF-01
A8: 4 | B8: INT-04 | C8: 1. Развёртывание | D8: CORS: preflight с origin фронтенда | E8: OPTIONS /api/images/build с Origin http://localhost:5173 | F8: 200, Access-Control-Allow-Origin = origin | G8: HTTP 200, ACAO=http://localhost:5173 | H8: PASS | I8: 0.02
A9: 5 | B9: INT-05 | C9: 1. Развёртывание | D9: CORS: origin боевого домена | E9: OPTIONS с Origin https://builder.example.com (фронт на домене/другом порту) | F9: Разрешённые origin задаются конфигурацией (переменной окружения) | G9: HTTP 403 «Invalid CORS request» — фронт на любом другом адресе не сможет обращаться к API; origin изменить без пересборки нельзя | H9: FAIL | I9: 0.01 | J9: DEF-02
A10: 6 | B10: INT-06 | C10: 1. Развёртывание | D10: Схема БД создана Hibernate на чистой MySQL | E10: Проверка таблиц и ограничений в information_schema | F10: Все таблицы есть, уникальный индекс на User.email | G10: 11 таблиц, уникальный индекс email есть | H10: PASS | I10: 0.03
A11: 7 | B11: INT-07 | C11: 1. Развёртывание | D11: Начальное наполнение (DataSeeder) через конвейер сборки | E11: На чистой БД: каталог, администратор, стартовые образы проходят реальную очередь сборки | F11: 67 компонентов, 15 образов; все стартовые образы READY и скачиваемы | G11: 67 компонентов, 15/15 образов READY (очередь опустела за 0 с), вход admin OK | H11: PASS | I11: 0.58
A12: 8 | B12: INT-08 | C12: 2. Аутентификация и доступ | D12: Регистрация и вход | E12: POST /auth/register, затем POST /auth/login и GET /users/me | F12: 200, JWT, профиль с ролью USER | G12: токен выдан, /users/me → it-c28bab-117d46@test.io ['USER'] | H12: PASS | I12: 0.46
A13: 9 | B13: INT-09 | C13: 2. Аутентификация и доступ | D13: Валидация регистрации | E13: Слабый пароль, неверный email, пустое имя, дубликат email | F13: 400 с понятным сообщением для каждого случая | G13: weak password→400, bad email→400, empty name→400, duplicate→400 | H13: PASS | I13: 0.22
A14: 10 | B14: INT-10 | C14: 2. Аутентификация и доступ | D14: Вход с неверным паролем / несуществующим email | E14: POST /auth/login с неверными учётными данными | F14: 401 Unauthorized с сообщением об ошибке | G14: неверный пароль → HTTP 403 «»; нет пользователя → HTTP 403 | H14: FAIL | I14: 0.23 | J14: DEF-03
A15: 11 | B15: INT-11 | C15: 2. Аутентификация и доступ | D15: Доступ к защищённым ресурсам без токена | E15: GET /users/me, POST /images/build без Authorization | F15: 401 (фронтенд перенаправляет на вход только по 401) | G15: /users/me → 403, /images/build → 403 | H15: FAIL | I15: 0.01 | J15: DEF-04
A16: 12 | B16: INT-12 | C16: 2. Аутентификация и доступ | D16: Повреждённый и чужой по подписи токен | E16: Authorization: Bearer <мусор>; токен, подписанный другим ключом | F16: 401, без 500 и стектрейсов | G16: коды: {'мусор': 403, 'чужая подпись': 403} | H16: FAIL | I16: 0.04 | J16: DEF-05
A17: 13 | B17: INT-13 | C17: 2. Аутентификация и доступ | D17: Просроченный токен | E17: Токен с exp в прошлом (подписан ключом приложения) | F17: 401 → фронтенд отправляет на вход | G17: HTTP 403 (ExpiredJwtException не обработано) | H17: FAIL | I17: 0.02 | J17: DEF-05
A18: 14 | B18: INT-14 | C18: 2. Аутентификация и доступ | D18: Время жизни JWT | E18: Декодирование выданного токена: exp - iat | F18: 24 часа (так указано в коде/документации) | G18: 4.0 ч | H18: FAIL | I18: 0.12 | J18: DEF-06
A19: 15 | B19: INT-15 | C19: 2. Аутентификация и доступ | D19: Ключ подписи JWT в исходном коде | E19: Токен, подписанный ключом из репозитория, принимается сервером | F19: Ключ берётся из секрета окружения; такой токен отклоняется | G19: GET /users (ADMIN) с токеном из известного ключа → HTTP 200 | H19: FAIL | I19: 0.09 | J19: DEF-07
A20: 16 | B20: INT-16 | C20: 2. Аутентификация и доступ | D20: Разграничение ролей USER / ADMIN | E20: USER вызывает админские операции: GET /users, POST /components, PUT/DELETE /images/{id} | F20: 403 для всех | G20: GET /users→403, POST /components→403, PUT /images→403, DELETE /images→403, DELETE /users/1→403 | H20: PASS | I20: 0.35
A21: 17 | B21: INT-17 | C21: 2. Аутентификация и доступ | D21: Токен удалённого пользователя | E21: Админ удаляет пользователя, тот продолжает запрос со старым токеном | F21: 401 | G21: HTTP 403 | H21: FAIL | I21: 0.37 | J21: DEF-08
A22: 18 | B22: INT-18 | C22: 2. Аутентификация и доступ | D22: Гонка: одновременная регистрация одного email | E22: 20 параллельных POST /auth/register с одинаковым email | F22: Ровно 1 успех, остальные 400/409, дублей в БД нет, 5xx нет | G22: коды {200: 1, 409: 9, 400: 10}, строк в БД 1 | H22: PASS | I22: 0.23
A23: 19 | B23: INT-19 | C23: 3. Каталог и пагинация | D23: Пагинация: граничные значения | E23: size=1000, size=0, page=-1, page за пределами | F23: size обрезается до 100, page<0 → 0, пустая страница за пределами | G23: size 1000→100, 0→1, page -1→0, page 999 → пусто | H23: PASS | I23: 0.14
A24: 20 | B24: INT-20 | C24: 3. Каталог и пагинация | D24: Нечисловые параметры (анонимный пользователь) | E24: GET /components?page=abc, GET /images?components=x, GET /components/abc | F24: 400 Bad Request | G24: {'page=abc': 403, 'components=x': 403, '/components/abc': 403} | H24: FAIL | I24: 0.03 | J24: DEF-10
A25: 21 | B25: INT-21 | C25: 3. Каталог и пагинация | D25: Спецсимволы и инъекции в поиске | E25: search = ', ", ' OR 1=1 --, %, _, <script> | F25: Нет 5xx; спецсимволы трактуются буквально (% и _ не шаблоны) | G25: инъекции нет (параметризованные запросы), но wildcard: найдено {"'": 0, '"': 0, "' OR 1=1 --": 0, '<script>': 0, '%': 67, '_': 67} | H25: FAIL | I25: 0.14 | J25: DEF-11
A26: 22 | B26: INT-22 | C26: 3. Каталог и пагинация | D26: Комбинация поиска, типа, сортировки и страниц | E26: Сквозной проход всех страниц с search+type+sort=price_desc | F26: Без дублей и пропусков, порядок по цене сохраняется между страницами | G26: 30 записей на 5 стр., дублей нет | H26: PASS | I26: 0.11
A27: 23 | B27: INT-23 | C27: 3. Каталог и пагинация | D27: Число SQL-запросов на одну страницу образов | E27: Дельта счётчика Questions MySQL вокруг GET /images?size=12 | F27: ≤ 10 запросов (без проблемы N+1) | G27: GET /images?size=12 → 23 SQL-запросов; GET /components?size=20 → 31 | H27: FAIL | I27: 0.15 | J27: DEF-12
A28: 24 | B28: INT-24 | C28: 4. Компоненты (ADMIN) | D28: Создание компонента с зависимостями и чтение | E28: POST /components с dependencyIds, GET /components/{id} | F28: 201/200, зависимости сохранены | G28: HTTP 200, id=68, deps=[1] | H28: PASS | I28: 0.24
A29: 25 | B29: INT-25 | C29: 4. Компоненты (ADMIN) | D29: Защита графа зависимостей | E29: Зависимость на себя; цикл A→B→A через PUT | F29: 400 в обоих случаях, граф не меняется | G29: self→400, cycle→400 | H29: PASS | I29: 0.26
A30: 26 | B30: INT-26 | C30: 4. Компоненты (ADMIN) | D30: Удаление используемого и свободного компонента | E30: DELETE компонента, входящего в образ; DELETE свободного | F30: 400 с сообщением; 204 | G30: used→400 «Компонент «numpy» входит в образы — сначала измени», free→204, затем GET→404 | H30: PASS | I30: 0.3
A31: 27 | B31: INT-27 | C31: 4. Компоненты (ADMIN) | D31: Валидация полей компонента | E31: Пустое имя; отрицательная цена; имя 300 символов; несуществующий тип | F31: 400 для некорректных полей (404 допустим для несуществующего типа) | G31: {'empty name': 400, 'negative cost': 400, 'name 300': 409, 'bad type': 404} | H31: FAIL | I31: 0.22 | J31: DEF-13
A32: 28 | B32: INT-28 | C32: 4. Компоненты (ADMIN) | D32: Параллельное редактирование компонента двумя админами | E32: 10 одновременных PUT одного компонента с разными ценами | F32: Без 5xx; итог — одно из отправленных значений | G32: коды {200: 1, 409: 9}, итоговая цена 104: оптимистичная блокировка (@Version) отсекла конкурентные записи | H32: PASS | I32: 0.31
A33: 29 | B33: INT-29 | C33: 5. Заказ и сборка образа | D33: Заказ сборки с разрешением транзитивных зависимостей | E33: USER заказывает образ [opencv-python] | F33: 202, QUEUED, в составе numpy и python3, цена = сумма компонентов | G33: HTTP 202, state=QUEUED, состав=['numpy', 'opencv-python', 'python3'], cost=160 | H33: PASS | I33: 0.25
A34: 30 | B34: INT-30 | C34: 5. Заказ и сборка образа | D34: Сборка до READY и появление в «Мои образы» | E34: Опрос GET /images/{id} до финального статуса | F34: READY, downloadable=true, образ в /users/me/images | G34: READY за 2.1 с | H34: PASS | I34: 2.18
A35: 31 | B35: INT-31 | C35: 5. Заказ и сборка образа | D35: Скачивание артефакта и проверка содержимого | E35: GET /images/{id}/download владельцем; проверка ext4 и манифеста внутри образа | F35: 200, octet-stream, валидный ext4 (магия 0xEF53), размер 16+N МБ, манифест — валидный JSON с составом | G35: ext4 OK, 19 МБ, пакеты ['numpy', 'opencv-python', 'python3'], манифест: IT Образ «Тест» c28bab | H35: PASS | I35: 18.99
A36: 32 | B36: INT-32 | C36: 5. Заказ и сборка образа | D36: Имя файла при скачивании (кириллица) | E36: Заголовок Content-Disposition для образа «Образ для камеры» | F36: Корректное имя файла (filename*=UTF-8''… по RFC 6266) | G36: HTTP 200, заголовок Content-Disposition отсутствует (Tomcat отбросил значение с не-Latin-1 символами) — браузер сохранит файл как «download» | H36: FAIL | I36: 3.79 | J36: DEF-15
A37: 33 | B37: INT-33 | C37: 5. Заказ и сборка образа | D37: Скачивание чужого образа | E37: Другой USER скачивает образ первого пользователя | F37: 403 (скачивать может владелец или ADMIN) | G37: HTTP 200, получено 19 МБ чужого образа | H37: FAIL | I37: 0.3 | J37: DEF-16
A38: 34 | B38: INT-34 | C38: 5. Заказ и сборка образа | D38: Скачивание без токена и неготового образа | E38: GET /download анонимно; GET /download для QUEUED | F38: 401; 400 «не готов» | G38: аноним → HTTP 403; неготовый → 400 | H38: FAIL | I38: 0.14 | J38: DEF-04
A39: 35 | B39: INT-35 | C39: 5. Заказ и сборка образа | D39: Валидация заказа | E39: Пустой список компонентов; несуществующий компонент; пустое имя | F39: 400/404 без 5xx | G39: {'empty components': 400, 'unknown component': 404, 'empty name': 400} | H39: PASS | I39: 0.19
A40: 36 | B40: INT-36 | C40: 5. Заказ и сборка образа | D40: Очередь сборок: один воркер, FIFO | E40: 6 последовательных заказов + 6 одновременных от разных пользователей; мониторинг статусов каждые 0,3 с | F40: Одновременно BUILDING не более 1; последовательные заказы завершаются в порядке заказа; все READY | G40: max BUILDING=1, FIFO соблюдён, 12 сборок за 35.5 с (3.0 с/сборку); одновременные заказы выполняются в порядке фиксации транзакций, а не id: [25, 28, 26, 27, 29, 30] | H40: PASS | I40: 39.87
A41: 37 | B41: INT-37 | C41: 5. Заказ и сборка образа | D41: Изменение образа администратором с пересборкой | E41: PUT /images/{id} READY-образа (другой состав); проверка нового артефакта | F41: 202 → QUEUED → READY; новый состав в артефакте; старый файл заменён | G41: 202, пересобран за 3.6 с, состав ['glibc', 'openssh'], cost 60; PUT во время сборки → 400 | H41: PASS | I41: 3.99
A42: 38 | B42: INT-38 | C42: 5. Заказ и сборка образа | D42: Удаление образа администратором | E42: DELETE /images/{id}: запись, связь с пользователем и файл артефакта | F42: 204; GET → 404; файл удалён с диска; пропал из «Мои образы» | G42: 204, 404, файл удалён, связь с пользователем снята | H42: PASS | I42: 0.7
A43: 39 | B43: INT-39 | C43: 5. Заказ и сборка образа | D43: Удаление пользователя, у которого есть образы | E43: Админ удаляет пользователя с заказанными образами | F43: 204; образы остаются в библиотеке | G43: 204, образ сохранён | H43: PASS | I43: 0.39
A44: 40 | B44: INT-40 | C44: 5. Заказ и сборка образа | D44: Артефакт удалён с диска вне приложения | E44: Файл .img удаляется на сервере, затем GET /images/{id} и /download | F44: downloadable=false либо понятная ошибка; без 5xx | G44: downloadable=True, download → HTTP 400 {"error":"Файл артефакта не найден на сервере"} | H44: FAIL | I44: 6.47 | J44: DEF-17
A45: 41 | B45: INT-41 | C45: 6. Управление пользователями | D45: CRUD пользователей администратором | E45: POST → GET → PUT (роль ADMIN, пароль) → вход с новым паролем → DELETE | F45: 201/200 на каждом шаге, новые права действуют | G45: создан, повышен до ADMIN, вход с новым паролем, поиск+фильтр, удалён | H45: PASS | I45: 0.61
A46: 42 | B46: INT-42 | C46: 6. Управление пользователями | D46: Защита от самоблокировки администратора | E46: Админ удаляет себя; снимает с себя роль ADMIN | F46: 400 в обоих случаях | G46: 400 / 400 | H46: PASS | I46: 0.16
A47: 43 | B47: INT-43 | C47: 6. Управление пользователями | D47: Смена email администратором самому себе | E47: Админ меняет свой email через PUT /users/{id} | F47: Сессия продолжает работать (или выдаётся новый токен) | G47: PUT → 200, затем /users/me со старым токеном → 403 | H47: FAIL | I47: 0.31 | J47: DEF-18
A48: 44 | B48: INT-44 | C48: 7. Отказоустойчивость | D48: Перезапуск backend: сохранность данных | E48: Graceful-остановка (SIGTERM) и запуск jar; повторный старт DataSeeder | F48: Данные сохранены, дублей каталога нет, токен остаётся валидным | G48: компонентов/образов (71, 31) = до рестарта; простой 12 с; токен валиден | H48: PASS | I48: 12.16
A49: 45 | B49: INT-45 | C49: 7. Отказоустойчивость | D49: Падение backend (kill -9) во время сборки | E49: 3 заказа в очереди, kill -9 в момент BUILDING, запуск backend | F49: Прерванные сборки возобновляются или помечаются FAILED; их можно пересобрать/удалить | G49: через 15 с после рестарта статусы {33: 'BUILDING', 34: 'QUEUED', 35: 'QUEUED'}; попытки PUT/DELETE зависших: {33: (400, 400), 34: (400, 204), 35: (400, 204)} | H49: FAIL | I49: 26.61 | J49: DEF-19
A50: 46 | B50: INT-46 | C50: 7. Отказоустойчивость | D50: Недоступность БД | E50: Остановка MySQL; запросы к API; запуск MySQL; повтор запросов без рестарта backend | F50: Во время сбоя — быстрый 5xx (≤ 5 с) без утечки деталей; после восстановления — 200 без рестарта | G50: во время сбоя HTTP 403 за 28.3 с; восстановление без рестарта за 2.9 с | H50: FAIL | I50: 40.34 | J50: DEF-20
A51: 47 | B51: INT-47 | C51: 7. Отказоустойчивость | D51: Состояние стенда после всех тестов | E51: Ошибки в логе backend (ERROR/Exception), итоговые проверки API | F51: API отвечает, очередь пуста | G51: API отвечает | H51: PASS | I51: 0.01
A52: 48 | B52: E2E-01 | C52: 8. E2E через браузер (UI) | D52: Открытие главной, редирект в библиотеку, отрисовка карточек | E52: Переход на / без авторизации; ожидание первой карточки образа | F52: Редирект на /library/images, карточки отрисованы < 2 с | G52: /library/images, карточек 12, первая карточка через 412 мс (DOMContentLoaded 50 мс) | H52: PASS | I52: 0.42
A53: 49 | B53: E2E-02 | C53: 8. E2E через браузер (UI) | D53: Регистрация через форму | E53: Заполнение формы /register валидными данными | F53: Вход выполнен, токен сохранён, переход в библиотеку | G53: после регистрации → /library/images, токен в localStorage: true | H53: PASS | I53: 0.72
A54: 50 | B54: E2E-03 | C54: 8. E2E через браузер (UI) | D54: Фильтр по компоненту и сортировка по цене | E54: Выбор openssh в фильтре компонентов, сортировка «Цена: по убыванию» | F54: IoT Edge, Media Box (по убыванию цены) | G54: IoT Edge, Media Box | H54: PASS | I54: 3.36
A55: 51 | B55: E2E-04 | C55: 8. E2E через браузер (UI) | D55: Заказ сборки в редакторе | E55: Редактор образа: название, поиск ffmpeg в каталоге, добавление, «Собрать»; проверка в личном кабинете | F55: Образ появляется в «Мои образы», статус доходит до «Готов», зависимость glibc добавлена автоматически | G55: в кабинете: E2E образ | Готов | buildroot | RV1103_Luckfox_Pico | glibc | ffmpeg | 80 ед. | Скачать .img | H55: PASS | I55: 10.9
A56: 52 | B56: E2E-05 | C56: 8. E2E через браузер (UI) | D56: Скачивание .img из интерфейса | E56: Кнопка «Скачать .img» на карточке готового образа | F56: Браузер сохраняет файл <название>.img корректного размера | G56: файл «E2E образ.img», 18 874 368 байт (18 МБ = 16 + 2 компонента) | H56: PASS | I56: 0.56
A57: 53 | B57: E2E-06 | C57: 8. E2E через браузер (UI) | D57: Недействительный токен в браузере | E57: В localStorage подменён токен, открыт /account | F57: Сессия сбрасывается, редирект на /login | G57: пользователь остался на /account: «Request failed with status code 403 | Вы ещё не заказывали сборки» — API отвечает 403, а клиент перехватывает только 401 | H57: FAIL | I57: 2.67 | J57: DEF-04
A58: 54 | B58: E2E-07 | C58: 8. E2E через браузер (UI) | D58: Админ: страница пользователей и поиск | E58: Вход admin, /admin/users, поиск по «e2e-» | F58: Зарегистрированный в E2E-02 пользователь найден | G58: пользователь найден | H58: PASS | I58: 3.09
A59: 55 | B59: E2E-08 | C59: 8. E2E через браузер (UI) | D59: Неверный пароль в форме входа | E59: Вход admin с неверным паролем | F59: Понятное сообщение «Неверный email или пароль» | G59: показано техническое сообщение «Request failed with status code 403» | H59: FAIL | I59: 1.71 | J59: DEF-03
A60: 56 | B60: E2E-09 | C60: 8. E2E через браузер (UI) | D60: JS-ошибки за весь сценарий | E60: Подписка на pageerror во время E2E-01…08 | F60: Нет необработанных исключений JS | G60: нет | H60: PASS | I60: 0

Sheet Дефекты
A1: Реестр дефектов
A2: Серьёзность: Критическая — безопасность/потеря данных; Высокая — функция недоступна; Средняя — неверное поведение с обходом; Низкая — косметика/удобство.
A4: ID | B4: Серьёзность | C4: Описание | D4: Где обнаружен | E4: Рекомендация по исправлению | F4: Статус
A5: DEF-07 | B5: Критическая | C5: Секрет JWT захардкожен в JwtService и лежит в Git: любой, кто видел репозиторий, может выпустить токен администратора | D5: INT-15 | E5: Читать секрет из переменной окружения/секрета, сгенерировать новый, старый считать скомпрометированным | F5: Открыт
A6: DEF-05 | B6: Высокая | C6: Некорректный/поддельный/просроченный JWT приводит к исключению в JwtAuthenticationFilter (ответ 403/500 вместо 401), в лог пишется стектрейс | D6: INT-12, INT-13 | E6: Оборачивать разбор JWT в try/catch (JwtException) и продолжать цепочку как аноним → 401 | F6: Открыт
A7: DEF-16 | B7: Высокая | C7: Нет проверки владельца при скачивании: любой авторизованный пользователь скачивает чужие образы по id (IDOR) | D7: INT-33 | E7: В download проверять, что образ в orderedImages текущего пользователя или роль ADMIN | F7: Открыт
A8: DEF-19 | B8: Высокая | C8: Очередь сборок живёт только в памяти: после перезапуска/падения backend образы навсегда остаются QUEUED/BUILDING, их нельзя ни изменить, ни удалить (BUILDING), пользователь никогда не получит образ | D8: INT-45 | E8: При старте переводить BUILDING→FAILED и заново ставить QUEUED в очередь (ApplicationReadyEvent); либо хранить очередь в БД | F8: Открыт
A9: DEF-21 | B9: Высокая | C9: Нет ограничения частоты попыток входа: в L-06 за 4 мин с одного адреса принято 9 618 входов без блокировки и задержек. При 100 попытках/с BCrypt занимает ≈8 ядер, и вход остальных пользователей замедляется в 11 раз — возможны перебор паролей и отказ в обслуживании входа. | D9: L-06 | E9: Ограничение частоты для /api/auth/login по IP и email (Bucket4j, nginx limit_req), нарастающая задержка/блокировка после N неудач, ответ 429 | F9: Исправлен: 429 после 5 неудач (INT-48)
A10: DEF-02 | B10: Средняя | C10: Разрешённый CORS-origin захардкожен (http://localhost:5173) в WebConfig | D10: INT-05 | E10: Вынести список origin в application.properties/переменную окружения (CORS_ALLOWED_ORIGINS) | F10: Открыт
A11: DEF-03 | B11: Средняя | C11: Неверный логин/пароль возвращает 403 без тела вместо 401 | D11: INT-10, E2E-08 | E11: Обрабатывать AuthenticationException в GlobalExceptionHandler (401 + сообщение); разрешить /error в SecurityConfig | F11: Открыт
A12: DEF-04 | B12: Средняя | C12: Запрос без токена/с недействительным токеном получает 403 вместо 401 — фронтенд (interceptor по 401) не выкидывает пользователя на страницу входа | D12: INT-11, INT-34, E2E-06 | E12: Настроить authenticationEntryPoint (HttpStatusEntryPoint(UNAUTHORIZED)) в SecurityConfig | F12: Открыт
A13: DEF-08 | B13: Средняя | C13: Запрос с токеном удалённого пользователя: UsernameNotFoundException в фильтре → 403/500 | D13: INT-17 | E13: Ловить UsernameNotFoundException в JwtAuthenticationFilter и отвечать 401 | F13: Открыт
A14: DEF-10 | B14: Средняя | C14: Ошибки разбора параметров у анонимного пользователя возвращают 403 вместо 400 (ошибка уходит на /error, закрытый Spring Security) | D14: INT-20 | E14: Разрешить /error в SecurityConfig (permitAll) и обработать MethodArgumentTypeMismatchException → 400 | F14: Открыт
A15: DEF-12 | B15: Средняя | C15: N+1 запросов: список из 12 образов порождает десятки SQL-запросов (ленивые components и dependencies грузятся поштучно) | D15: INT-23 | E15: @EntityGraph / JOIN FETCH для components.type, batch-size для коллекций (hibernate.default_batch_fetch_size) | F15: Исправлен: 389 → 11 SQL (L-10b повторно)
... A26: DEF-23 | B26: Низкая | C26: Нет индексов для поиска, фильтра по статусу, сортировки по цене и глубокой пагинации: на 20 тыс. образов page=1500 замедлилась в 7,5 раза (OFFSET), сортировка по цене — filesort (34 мс), LIKE '%…%' — полное сканирование; count(*) на каждую страницу. | D26: L-10b | E26: Индексы Image(state, cost), Image(name), Component(type, cost); keyset-пагинация или ограничение максимального номера страницы; полнотекстовый поиск при росте каталога | F26: Частично: индексы добавлены, поиск по подстроке — полный проход

Sheet Оптимизация
A1: Оптимизация по итогам нагрузочного тестирования: до и после
A2: Те же профили k6 и стенд; «до» — версия 27e1fb0, «после» — с исправлениями ниже. Объёмный тест — та же БД ×100 (volume_seed.sql). Повторный интеграционный прогон — как и первый, на чистой БД после DataSeeder.
A4: 1. Внесённые исправления
A5: Изменение | B5: Дефект | C5: Файлы
A6: Пакетная догрузка ленивых связей: hibernate.default_batch_fetch_size=100 — components, dependencies и типы компонентов грузятся одним IN (...) на страницу вместо запроса на каждую строку | B6: DEF-12, DEF-22 | C6: application.properties
A7: Отключён Open Session In View (spring.jpa.open-in-view=false): соединение с БД больше не удерживается до конца HTTP-запроса — в том числе на время проверки пароля BCrypt при входе | B7: DEF-22, DEF-21 | C7: application.properties
A8: Пользователь с ролями — одним JOIN (@EntityGraph на findByEmail): запрос выполняется JWT-фильтром на каждый авторизованный запрос | B8: DEF-22 | C8: UserRepository.java
A9: Соединения пула без autocommit (hikari.auto-commit=false + provider_disables_autocommit): минус SET autocommit=0/1 вокруг каждой транзакции | B9: DEF-22 | C9: application.properties
A10: Пул HikariCP 10 → 20 соединений; connection-timeout 30 → 3 с и ответ 503 + Retry-After при исчерпании пула (быстрый отказ вместо ожидания) | B10: DEF-22, DEF-20 | C10: application.properties, GlobalExceptionHandler.java
A11: Индексы Image(state, cost), Image(cost), Component(name, id), Component(type, cost) — фильтр по статусу, сортировка по цене и названию без filesort | B11: DEF-23 | C11: Image.java, Component.java
A12: Ограничение неудачных входов: 5 на email и 20 на IP за 5 мин, сверх лимита — 429 + Retry-After без проверки BCrypt | B12: DEF-21 | C12: LoginAttemptService.java, AuthenticationService.java, AuthController.java
A13: 84 модульных теста (JUnit 5 + Mockito) на сервисы, DTO, валидацию и обработчик ошибок: mvn test — 84/84 | B13: — | C13: backend/src/test/java/…
A15: 2а. Одиночные запросы каталога, стартовая БД (388 образов): SQL на HTTP-запрос и задержка
A16: Запрос | C16: SQL до | D16: SQL после | E16: p95 до, мс | F16: p95 после, мс | G16: Ускорение p95, раз | H16: Итог
A17: Образы: первая страница (12) | C17: 28 | D17: 9 | E17: 10.5 | F17: 3.5 | G17: =IF(F17=0,0,E17/F17) -> 3 | H17: =IF(OR(E17="",F17=""),"—",IF(F17<E17,"лучше",IF(F17=E17,"без изменений","хуже"))) -> лучше
A18: Образы: страница 100 макс. размера | C18: 116 | D18: 9 | E18: 44.2 | F18: 5.7 | G18: =IF(F18=0,0,E18/F18) -> 7.754386 | H18: =IF(OR(E18="",F18=""),"—",IF(F18<E18,"лучше",IF(F18=E18,"без изменений","хуже"))) -> лучше
A19: Образы: глубокая страница (page=1500) | C19: 9 | D19: 7 | E19: 3.9 | F19: 2.8 | G19: =IF(F19=0,0,E19/F19) -> 1.3928571 | H19: =IF(OR(E19="",F19=""),"—",IF(F19<E19,"лучше",IF(F19=E19,"без изменений","хуже"))) -> лучше
A20: Образы: поиск по подстроке | C20: 8 | D20: 6 | E20: 3.1 | F20: 2.5 | G20: =IF(F20=0,0,E20/F20) -> 1.24 | H20: =IF(OR(E20="",F20=""),"—",IF(F20<E20,"лучше",IF(F20=E20,"без изменений","хуже"))) -> лучше
A21: Образы: фильтр по 2 компонентам | C21: 28 | D21: 9 | E21: 10.4 | F21: 5.6 | G21: =IF(F21=0,0,E21/F21) -> 1.8571429 | H21: =IF(OR(E21="",F21=""),"—",IF(F21<E21,"лучше",IF(F21=E21,"без изменений","хуже"))) -> лучше
A22: Образы: сортировка по цене ↓ + статус | C22: 27 | D22: 9 | E22: 9.6 | F22: 5.2 | G22: =IF(F22=0,0,E22/F22) -> 1.8461538 | H22: =IF(OR(E22="",F22=""),"—",IF(F22<E22,"лучше",IF(F22=E22,"без изменений","хуже"))) -> лучше
A23: Компоненты: первая страница | C23: 23 | D23: 9 | E23: 6.7 | F23: 3 | G23: =IF(F23=0,0,E23/F23) -> 2.2333333 | H23: =IF(OR(E23="",F23=""),"—",IF(F23<E23,"лучше",IF(F23=E23,"без изменений","хуже"))) -> лучше
A24: Компоненты: поиск + тип + цена ↑ | C24: 8 | D24: 6 | E24: 2.6 | F24: 2.3 | G24: =IF(F24=0,0,E24/F24) -> 1.1304348 | H24: =IF(OR(E24="",F24=""),"—",IF(F24<E24,"лучше",IF(F24=E24,"без изменений","хуже"))) -> лучше
A25: Пользователи (ADMIN): поиск | C25: 10 | D25: 8 | E25: 5 | F25: 5.9 | G25: =IF(F25=0,0,E25/F25) -> 0.84745763 | H25: =IF(OR(E25="",F25=""),"—",IF(F25<E25,"лучше",IF(F25=E25,"без изменений","хуже"))) -> хуже
A33: 2б. Одиночные запросы каталога, БД ×100 (20 тыс. образов): SQL на HTTP-запрос и задержка
A34: Запрос | C34: SQL до | D34: SQL после | E34: p95 до, мс | F34: p95 после, мс | G34: Ускорение p95, раз | H34: Итог
A35: Образы: первая страница (12) | C35: 56 | D35: 9 | E35: 17.9 | F35: 6 | G35: =IF(F35=0,0,E35/F35) -> 2.9833333 | H35: =IF(OR(E35="",F35=""),"—",IF(F35<E35,"лучше",IF(F35=E35,"без изменений","хуже"))) -> лучше
A36: Образы: страница 100 макс. размера | C36: 389 | D36: 11 | E36: 102.8 | F36: 11.8 | G36: =IF(F36=0,0,E36/F36) -> 8.7118644 | H36: =IF(OR(E36="",F36=""),"—",IF(F36<E36,"лучше",IF(F36=E36,"без изменений","хуже"))) -> лучше
A37: Образы: глубокая страница (page=1500) | C37: 57 | D37: 9 | E37: 26.9 | F37: 17.7 | G37: =IF(F37=0,0,E37/F37) -> 1.519774 | H37: =IF(OR(E37="",F37=""),"—",IF(F37<E37,"лучше",IF(F37=E37,"без изменений","хуже"))) -> лучше
A38: Образы: поиск по подстроке | C38: 56 | D38: 9 | E38: 32.8 | F38: 12.2 | G38: =IF(F38=0,0,E38/F38) -> 2.6885246 | H38: =IF(OR(E38="",F38=""),"—",IF(F38<E38,"лучше",IF(F38=E38,"без изменений","хуже"))) -> лучше
A39: Образы: фильтр по 2 компонентам | C39: 28 | D39: 9 | E39: 10.4 | F39: 5.8 | G39: =IF(F39=0,0,E39/F39) -> 1.7931034 | H39: =IF(OR(E39="",F39=""),"—",IF(F39<E39,"лучше",IF(F39=E39,"без изменений","хуже"))) -> лучше
A40: Образы: сортировка по цене ↓ + статус | C40: 57 | D40: 9 | E40: 35.7 | F40: 7.4 | G40: =IF(F40=0,0,E40/F40) -> 4.8243243 | H40: =IF(OR(E40="",F40=""),"—",IF(F40<E40,"лучше",IF(F40=E40,"без изменений","хуже"))) -> лучше
A41: Компоненты: первая страница | C41: 23 | D41: 9 | E41: 7.4 | F41: 3.4 | G41: =IF(F41=0,0,E41/F41) -> 2.1764706 | H41: =IF(OR(E41="",F41=""),"—",IF(F41<E41,"лучше",IF(F41=E41,"без изменений","хуже"))) -> лучше
A42: Компоненты: поиск + тип + цена ↑ | C42: 22 | D42: 9 | E42: 10.4 | F42: 5.1 | G42: =IF(F42=0,0,E42/F42) -> 2.0392157 | H42: =IF(OR(E42="",F42=""),"—",IF(F42<E42,"лучше",IF(F42=E42,"без изменений","хуже"))) -> лучше
A43: Пользователи (ADMIN): поиск | C43: 31 | D43: 10 | E43: 14.8 | F43: 12.3 | G43: =IF(F43=0,0,E43/F43) -> 1.203252 | H43: =IF(OR(E43="",F43=""),"—",IF(F43<E43,"лучше",IF(F43=E43,"без изменений","хуже"))) -> лучше
A51: 3. Под нагрузкой: ключевые показатели профилей до и после
A52: Профиль | B52: Показатель | C52: До | D52: После | E52: Изменение | F52: Итог
A53: L-04b Стресс до отказа (breakpoint) | B53: Макс. пропускная способность, запросов/с | C53: 1468.1 | D53: 3829.6 | E53: =IF(OR(C53="",C53=0,D53=""),"—",(D53-C53)/C53) -> 1.6085417 | F53: =IF(OR(C53="",D53=""),"—",IF(D53>C53,"лучше",IF(D53=C53,"без изменений","хуже"))) -> лучше
A54: L-04b Стресс до отказа (breakpoint) | B54: Медиана на ступени 1 500 ит/с, мс | C54: 2732.2 | D54: 3.2 | E54: =IF(OR(C54="",C54=0,D54=""),"—",(D54-C54)/C54) -> -0.99882878 | F54: =IF(OR(C54="",D54=""),"—",IF(D54<C54,"лучше",IF(D54=C54,"без изменений","хуже"))) -> лучше
A55: L-04b Стресс до отказа (breakpoint) | B55: Медиана на ступени 2 000 ит/с, мс | C55: 2692 | D55: 3.4 | E55: =IF(OR(C55="",C55=0,D55=""),"—",(D55-C55)/C55) -> -0.998737 | F55: =IF(OR(C55="",D55=""),"—",IF(D55<C55,"лучше",IF(D55=C55,"без изменений","хуже"))) -> лучше
A56: L-04b Стресс до отказа (breakpoint) | B56: Медиана на ступени 4 000 ит/с, мс | C56: 2138.2 | D56: 826.7 | E56: =IF(OR(C56="",C56=0,D56=""),"—",(D56-C56)/C56) -> -0.61336638 | F56: =IF(OR(C56="",D56=""),"—",IF(D56<C56,"лучше",IF(D56=C56,"без изменений","хуже"))) -> лучше
A57: L-04b Стресс до отказа (breakpoint) | B57: Ошибки, % | C57: 0 | D57: 0 | E57: =IF(OR(C57="",C57=0,D57=""),"—",(D57-C57)/C57) -> — | F57: =IF(OR(C57="",D57=""),"—",IF(D57<C57,"лучше",IF(D57=C57,"без изменений","хуже"))) -> без изменений
A58: L-04b Стресс до отказа (breakpoint) | B58: SQL-запросов на HTTP-запрос | C58: 12.6 | D58: 5.6 | E58: =IF(OR(C58="",C58=0,D58=""),"—",(D58-C58)/C58) -> -0.55555556 | F58: =IF(OR(C58="",D58=""),"—",IF(D58<C58,"лучше",IF(D58=C58,"без изменений","хуже"))) -> лучше
A59: L-04 Стресс (поиск предела) | B59: p95 за профиль, мс | C59: 15.02 | D59: 6.86 | E59: =IF(OR(C59="",C59=0,D59=""),"—",(D59-C59)/C59) -> -0.54327563 | F59: =IF(OR(C59="",D59=""),"—",IF(D59<C59,"лучше",IF(D59=C59,"без изменений","хуже"))) -> лучше
A60: L-04 Стресс (поиск предела) | B60: p95 на ступени 600 ит/с, мс | C60: 12.4 | D60: 6.3 | E60: =IF(OR(C60="",C60=0,D60=""),"—",(D60-C60)/C60) -> -0.49193548 | F60: =IF(OR(C60="",D60=""),"—",IF(D60<C60,"лучше",IF(D60=C60,"без изменений","хуже"))) -> лучше
A61: L-04 Стресс (поиск предела) | B61: CPU mysqld средн., % | C61: 97.4 | D61: 55.7 | E61: =IF(OR(C61="",C61=0,D61=""),"—",(D61-C61)/C61) -> -0.42813142 | F61: =IF(OR(C61="",D61=""),"—",IF(D61<C61,"лучше",IF(D61=C61,"без изменений","хуже"))) -> лучше
A62: L-04 Стресс (поиск предела) | B62: CPU java средн., % | C62: 80.1 | D62: 55.8 | E62: =IF(OR(C62="",C62=0,D62=""),"—",(D62-C62)/C62) -> -0.30337079 | F62: =IF(OR(C62="",D62=""),"—",IF(D62<C62,"лучше",IF(D62=C62,"без изменений","хуже"))) -> лучше
A63: L-04 Стресс (поиск предела) | B63: SQL-запросов на HTTP-запрос | C63: 12.5 | D63: 5.6 | E63: =IF(OR(C63="",C63=0,D63=""),"—",(D63-C63)/C63) -> -0.552 | F63: =IF(OR(C63="",D63=""),"—",IF(D63<C63,"лучше",IF(D63=C63,"без изменений","хуже"))) -> лучше
A64: L-10a Объём: базовая БД | B64: p95, мс (стартовая БД, 40 запросов/с) | C64: 9.19 | D64: 7.93 | E64: =IF(OR(C64="",C64=0,D64=""),"—",(D64-C64)/C64) -> -0.13710555 | F64: =IF(OR(C64="",D64=""),"—",IF(D64<C64,"лучше",IF(D64=C64,"без изменений","хуже"))) -> лучше
A65: L-10b Объём: БД ×100 | B65: p95, мс (БД ×100, 40 запросов/с) | C65: 27.71 | D65: 29.81 | E65: =IF(OR(C65="",C65=0,D65=""),"—",(D65-C65)/C65) -> 0.075784915 | F65: =IF(OR(C65="",D65=""),"—",IF(D65<C65,"лучше",IF(D65=C65,"без изменений","хуже"))) -> хуже
... A73: L-06 Шторм авторизаций | B73: Ошибки, % | C73: 0 | D73: 0 | E73: =IF(OR(C73="",C73=0,D73=""),"—",(D73-C73)/C73) -> — | F73: =IF(OR(C73="",D73=""),"—",IF(D73<C73,"лучше",IF(D73=C73,"без изменений","хуже"))) -> без изменений
A75: 4а. L-04b Стресс до отказа: ступени до и после
A76: Цель, итераций/с | B76: Достигнуто до, /с | C76: Достигнуто после, /с | D76: Med до, мс | E76: Med после, мс | F76: p95 до, мс | G76: p95 после, мс | H76: Ошибки после
A77: 1000 | B77: 1283.6 | C77: 1308.3 | D77: 3.8 | E77: 3.1 | F77: 11.7 | G77: 5.9 | H77: 0
A78: 1500 | B78: 1168.5 | C78: 1973 | D78: 2732.2 | E78: 3.2 | F78: 3101.4 | G78: 6.8 | H78: 0
A79: 2000 | B79: 1213.4 | C79: 2695.8 | D79: 2692 | E79: 3.4 | F79: 3047.3 | G79: 9.6 | H79: 0
A80: 3000 | B80: 1403.8 | C80: 3737.6 | D80: 2275.8 | E80: 36.2 | F80: 2648.9 | G80: 712.7 | H80: 0
A81: 4000 | B81: 1468.1 | C81: 3829.6 | D81: 2138.2 | E81: 826.7 | F81: 2496.4 | G81: 1044.2 | H81: 0
A93: 4б. L-04 Стресс: ступени до и после
A94: Цель, итераций/с | B94: Достигнуто до, /с | C94: Достигнуто после, /с | D94: Med до, мс | E94: Med после, мс | F94: p95 до, мс | G94: p95 после, мс | H94: Ошибки после
A95: 50 | B95: 64.6 | C95: 66.8 | D95: 5.5 | E95: 4.9 | F95: 16.2 | G95: 7.9 | H95: 0
A96: 100 | B96: 131.2 | C96: 133.4 | D96: 5.3 | E96: 4.7 | F96: 15.8 | G96: 7.6 | H96: 0
A97: 200 | B97: 258 | C97: 269.9 | D97: 4.9 | E97: 4.3 | F97: 15.4 | G97: 7.1 | H97: 0
A98: 300 | B98: 402.9 | C98: 417.9 | D98: 5 | E98: 4 | F98: 15.5 | G98: 6.8 | H98: 0
A99: 450 | B99: 606.2 | C99: 627.7 | D99: 4.6 | E99: 3.9 | F99: 14.9 | G99: 6.9 | H99: 0
A100: 600 | B100: 755.2 | C100: 777.9 | D100: 3.9 | E100: 3.6 | F100: 12.4 | G100: 6.3 | H100: 0
A111: 5. Регрессия: повторный интеграционный прогон на исправленной версии
A112: Прогон | B112: Тестов | C112: PASS | D112: FAIL
A113: До исправлений | B113: 47 | C113: 27 | D113: 20
A114: После исправлений | B114: 48 | C114: 30 | D114: 18
A116: Тест | B116: ID | C116: До | D116: После | E116: Результат после исправлений
A117: Защита от перебора паролей | B117: INT-48 | C117: новый | D117: PASS | E117: попытки [403, 403, 403, 403, 403, 429, 429]; верный пароль в окне блокировки → 429, Retry-After 300 с; другой пользователь вошёл
A118: Число SQL-запросов на одну страницу образов | B118: INT-23 | C118: FAIL | D118: PASS | E118: 9 / 9
A119: Недоступность БД | B119: INT-46 | C119: FAIL | D119: PASS | E119: 503 за 3.0 с; восстановление 1.0 с
A121: 6. Выводы
A122: • Предел пропускной способности чтения вырос в 2,6 раза: 1 470 → 3 830 запросов/с (L-04b). На ступенях 1 500 и 2 000 итераций/с медиана упала с 2,7 с до 3,2–3,4 мс — система больше не копит очередь; пропущенных итераций k6 — 526 тыс. → 81 тыс. Новый предел упирается в CPU машины (backend до 11 ядер, генератор нагрузки на той же машине), а не в пул БД.
A123: • На одинаковой нагрузке ресурсов нужно вдвое меньше: в L-04 (до 780 запросов/с) p95 15,0 → 6,9 мс, SQL-запросов/с 4 291 → 1 970, CPU mysqld 97 → 56 %, CPU backend 80 → 56 %.
A124: • Целевой профиль L-03 (100 одновременных пользователей): p95 17,5 → 5,6 мс, p99 34,4 → 16,3 мс, CPU backend 26 → 13 %, CPU mysqld 20 → 8 %.
A125: • Шторм входов L-06: на 100 входах/с медиана 912 → 104 мс, p95 1 050 → 127 мс, пропущенных итераций 56 → 0. Причина прежнего «колена» — Open Session In View: соединение с БД удерживалось всё время проверки пароля BCrypt, и 100 входов/с исчерпывали пул из 10 соединений. Предел входов теперь задаёт только CPU (BCrypt).
A126: • N+1 устранён: число SQL на страницу больше не зависит от её размера — 9–11 запросов на любую страницу (было 23–389). Страница из 100 образов на БД ×100: 389 → 11 SQL, p95 102,8 → 11,8 мс. Одиночные запросы на стартовой БД ускорились в 2–3 раза, хотя образов стало больше (388 → 508, добавились сборки из L-03). Единственное «хуже» среди одиночных запросов — поиск пользователей на стартовой БД (p95 5,0 → 5,9 мс, в пределах разброса).
A127: • Не улучшилось: p95 объёмного профиля L-10b под нагрузкой (27,7 → 29,8 мс, в пределах разброса) при снижении SQL/с на 66 %. На 20 тыс. образов время ответа определяют поиск по подстроке LIKE '%…%' и count(*) — полный проход таблицы, который индексами не лечится. Дальше — полнотекстовый индекс (FULLTEXT ngram) и keyset-пагинация (DEF-23, частично).
A128: • Регрессий нет. Повторный интеграционный прогон на чистой БД: изменились только INT-23 (N+1) и INT-46 (недоступная БД: 503 за 3,0 с вместо 403 через ~30 с) — FAIL → PASS, новый INT-48 (перебор паролей) — PASS; остальные результаты совпали с первым прогоном. LazyInitializationException после отключения Open Session In View — ни одного. Ни в одном из 6 повторных нагрузочных профилей нет HTTP-ошибок. Модульные тесты — 84/84.
A129: • Не исправлялось (вне задачи оптимизации или архитектурное): очередь сборок с одним воркером (DEF-24 — SDK использует общий каталог), дефекты безопасности и обработки ошибок (DEF-03/04/05/07/16/19).

Sheet Нагрузка — сценарии
A1: Сценарии нагрузочного тестирования (k6)
A2: Скрипт: tests/load/scenarios.js, запуск: tests/load/run_load.sh <профиль>
A4: ID | B4: Профиль | C4: Цель | D4: Модель нагрузки | E4: Действия виртуальных пользователей | F4: Критерии успеха (SLA)
A5: L-01 | B5: Дымовой (baseline) (PROFILE=smoke) | C5: Проверить работоспособность всех пользовательских путей под минимальной нагрузкой и получить эталонные времена отклика. | D5: constant-vus: 1 VU, 1 мин, пауза 1 с между итерациями | E5: Открытие сайта + ассеты → библиотека образов и компонентов → типы → вход → профиль → «Мои образы» → список пользователей (ADMIN); каждая 5-я итерация — заказ сборки, ожидание READY и скачивание | F5: ошибки < 1 %; p95 < 300 мс
A6: L-02 | B6: Просмотр каталогов (гости) (PROFILE=browse) | C6: Типовая нагрузка анонимных посетителей: чтение каталогов с поиском, фильтрами, сортировкой и пагинацией. | D6: ramping-vus: 0→50 VU за 1 мин, 3 мин удержание, 30 с спад; «время на чтение» 1–3 с | E6: Библиотека образов (случайные search/state/sort/page, 30 % — фильтр по 2 компонентам), 40 % — карточка образа, 50 % — библиотека компонентов, 20 % — типы | F6: ошибки < 1 %; p95 чтения < 500 мс
A7: L-03 | B7: Смешанный продакшен-профиль (целевая нагрузка) (PROFILE=mixed) | C7: Ожидаемая пиковая нагрузка: 100 одновременных пользователей разных ролей работают параллельно. | D7: 4 параллельных сценария, ramping-vus 1 мин разгон, 5 мин удержание: гости 70 VU, пользователи 20 VU, заказчики сборок 8 VU, администраторы 2 VU | E7: Гости — как L-02; пользователи — вход, профиль, «Мои образы», каталоги; заказчики — каталог → заказ сборки → опрос статуса каждые 2 с → скачивание 18–19 МБ; админы — список пользователей, создание/изменение/удаление компонента | F7: ошибки < 1 %; p95 чтения < 500 мс; p95 записи < 1000 мс
A8: L-04 | B8: Стресс (поиск предела) (PROFILE=stress) | C8: Найти точку насыщения: при какой интенсивности растёт задержка и появляются ошибки. | D8: ramping-arrival-rate без пауз: ступени 50 → 100 → 200 → 300 → 450 → 600 итераций/с по 1 мин (30 с разгон между ступенями), до 1500 VU | E8: Только чтение: 55 % библиотека образов (с фильтрами), 35 % компоненты, 5 % типы, 5 % HTML-страница; одна итерация ≈ 1,3 HTTP-запроса (часть итераций дополнительно открывает карточку) | F8: ошибки < 1 %; p95 < 500 мс (ожидается нарушение на верхних ступенях)
A9: L-04b | B9: Стресс до отказа (breakpoint) (PROFILE=breakpoint) | C9: Продолжение L-04: найти предел пропускной способности чтения, при котором растут задержки/ошибки. | D9: ramping-arrival-rate без пауз: ступени 1000 → 1500 → 2000 → 3000 → 4000 итераций/с по 1 мин, до 3000 VU | E9: Как в L-04 (одна итерация ≈ 1,3 HTTP-запроса) | F9: фиксация точки насыщения (ошибки ≥ 1 % или p95 ≥ 500 мс)
A10: L-05 | B10: Всплеск (spike) (PROFILE=spike) | C10: Проверить реакцию на резкий наплыв (например, ссылка в соцсети) и восстановление после него. | D10: ramping-vus: 10 VU 1 мин → 400 VU за 10 с → 1 мин удержание → 10 VU за 10 с → 1 мин | E10: Гости с короткими паузами 0,5–1,5 с: образы, компоненты, карточки | F10: ошибки < 1 %; p95 < 500 мс; после всплеска задержка возвращается к исходной
A11: L-06 | B11: Шторм авторизаций (PROFILE=login) | C11: Оценить пропускную способность входа (BCrypt — CPU-ёмкая операция) — например, утренний наплыв. | D11: ramping-arrival-rate: 10 → 25 → 50 → 100 входов/с по 30 с | E11: POST /auth/login существующими пользователями (50 учётных записей) | F11: ошибки < 1 %; p95 входа < 1000 мс
A12: L-07 | B12: Пакет заказов сборки (очередь) (PROFILE=burst) | C12: 60 пользователей одновременно заказывают сборку: проверка очереди с одним воркером, времени ожидания и отсутствия потерь. | D12: per-vu-iterations: 60 VU × 1 заказ, опрос статуса каждые 2 с до READY (макс. 20 мин) | E12: POST /images/build → опрос GET /images/{id} | F12: ошибки < 1 %; p95 заказа < 1000 мс; все 60 образов READY
A13: L-08 | B13: Скачивание артефактов (PROFILE=download) | C13: Нагрузка на отдачу больших файлов (.img 17–19 МБ): пропускная способность и влияние на API. | D13: constant-vus: 20 VU, 2 мин, пауза 0,5–1,5 с | E13: GET /images/{id}/download случайного готового образа | F13: ошибки < 1 %; p95 < 3000 мс
A14: L-09 | B14: Длительная нагрузка (soak) (PROFILE=soak) | C14: Выявить деградацию во времени: утечки памяти, рост задержек, исчерпание соединений. | D14: constant-vus 15 мин: гости 28, пользователи 8, заказчики 3, админ 1 (40 VU) | E14: Как в L-03 | F14: ошибки < 1 %; p95 чтения < 500 мс; нет роста heap/RSS и задержки к концу
A15: L-10a | B15: Объём: базовая БД (PROFILE=volume_base) | C15: Эталон для объёмного теста — чтение каталогов на стартовых данных при фиксированной интенсивности. | D15: constant-arrival-rate: 40 запросов/с, 3 мин | E15: Как в L-04 (только чтение) | F15: ошибки < 1 %; p95 < 500 мс
A16: L-10b | B16: Объём: БД ×100 (PROFILE=volume) | C16: То же при объёме данных, близком к продакшену через 1–2 года (20 000 образов, 2 000 компонентов, 5 000 пользователей). | D16: constant-arrival-rate: 40 запросов/с, 3 мин | E16: Как в L-04 (только чтение) | F16: ошибки < 1 %; p95 < 500 мс

Sheet Нагрузка — итоги
A1: Итоги нагрузочных профилей
A2: Задержки — http_req_duration k6 (мс). Ресурсы — посекундный мониторинг /proc + jstat + SHOW GLOBAL STATUS. CPU процесса: 100 % = 1 ядро (всего 16 логических).
A4: ID | B4: Профиль | C4: Длит., с | D4: Запросов | E4: Итераций | F4: RPS средн. | G4: RPS пик | H4: VU макс. | I4: Ошибки | J4: Коды ответа | K4: Avg, мс | L4: Min, мс | M4: Med, мс | N4: p95, мс | O4: p99, мс | P4: Max, мс | Q4: p90, мс | R4: Получено, МБ | S4: МБ/с | T4: CPU java ср./макс., % | U4: CPU mysqld ср./макс., % | V4: CPU машины ср./макс., % | W4: Heap макс., МБ | X4: RSS java нач.→кон., МБ | Y4: GC (кол-во / с) | Z4: Соед. БД макс. | AA4: SQL/с | AB4: SLA | AC4: Комментарий
A5: L-01 | B5: Дымовой (baseline) | C5: 56.3 | D5: 320 | E5: 28 | F5: 5.7 | G5: 16 | H5: 1 | I5: 0 | J5: 200: 314, 202: 6 | K5: 26.16 | L5: 0.76 | M5: 14.86 | N5: 111.47 | O5: 194.49 | P5: 360.56 | Q5: 107.19 | R5: 114.3 | S5: 2 | T5: 20.7 / 89.0 | U5: 3.2 / 11.0 | V5: 2.3 / 11.3 | W5: 193.9 | X5: 693.7 → 703.9 | Y5: 0 / 0.0 | Z5: 11 | AA5: 57 | AB5: PASS | AC5: Все пользовательские пути работают, 0 ошибок. Самые медленные — вход (≈110 мс, BCrypt) и скачивание образа.
A6: L-02 | B6: Просмотр каталогов (гости) | C6: 256.6 | D6: 7772 | E6: 3713 | F6: 30.3 | G6: 68 | H6: 50 | I6: 0 | J6: 200: 7772 | K6: 7.29 | L6: 0.29 | M6: 5.56 | N6: 15.28 | O6: 17.23 | P6: 34.19 | Q6: 13.92 | R6: 26.3 | S6: 0.1 | T6: 12.0 / 71.6 | U6: 9.6 / 20.6 | V6: 2.1 / 12.5 | W6: 318.3 | X6: 766.9 → 759.2 | Y6: 6 / 0.11 | Z6: 11 | AA6: 358.6 | AB6: PASS | AC6: 50 гостей ≈ 30 запросов/с: p95 15 мс, java ≈12 % одного ядра — запас многократный.
A7: L-03 | B7: Смешанный продакшен-профиль (целевая нагрузка) | C7: 373.3 | D7: 22489 | E7: 9139 | F7: 60.3 | G7: 149 | H7: 100 | I7: 0 | J7: 200: 22299, 202: 116, 204: 74 | K7: 8.88 | L7: 0.12 | M7: 6.06 | N7: 17.52 | O7: 34.41 | P7: 344.79 | Q7: 16.03 | R7: 2277.3 | S7: 6.1 | T7: 26.2 / 93.1 | U7: 20.1 / 33.5 | V7: 4.6 / 9.7 | W7: 334.8 | X7: 759.5 → 786.5 | Y7: 24 / 0.19 | Z7: 11 | AA7: 749.3 | AB7: PASS | AC7: Целевая нагрузка 100 VU: 0 ошибок из 22 489, p95 чтения 17,5 мс, записи < 60 мс. 116 сборок, среднее время до READY 12,5 с (до 8 заказов в очереди).
A8: L-04 | B8: Стресс (поиск предела) | C8: 513.4 | D8: 176498 | E8: 144374 | F8: 343.8 | G8: 1459 | H8: 100 | I8: 0 | J8: 200: 176498 | K8: 6.35 | L8: 0.09 | M8: 4.59 | N8: 15.02 | O8: 16.36 | P8: 56.94 | Q8: 13.17 | R8: 455.9 | S8: 0.9 | T8: 80.1 / 221.0 | U8: 97.4 / 233.2 | V8: 15.0 / 32.9 | W8: 335.9 | X8: 786.7 → 789.8 | Y8: 121 / 0.35 | Z8: 11 | AA8: 4290.8 | AB8: PASS | AC8: До 600 итераций/с (≈755 запросов/с) деградации нет: p95 12–16 мс. java ≈150 %, mysqld ≈230 %; ≈12,5 SQL на HTTP-запрос.
A9: L-04b | B9: Стресс до отказа (breakpoint) | C9: 433.2 | D9: 560700 | E9: 457947 | F9: 1294.4 | G9: 3800 | H9: 3000 | I9: 0 | J9: 200: 560700; пропущено итераций: 526012 | K9: 1718.14 | L9: 0.05 | M9: 2235.31 | N9: 2949.46 | O9: 3170.03 | P9: 4493.7 | Q9: 2845.76 | R9: 1482.8 | S9: 3.4 | T9: 324.8 / 441.2 | U9: 442.3 / 602.3 | V9: 68.9 / 85.2 | W9: 447.7 | X9: 838.2 → 980.6 | Y9: 415 / 2.08 | Z9: 11 | AA9: 16304.3 | AB9: FAIL | AC9: Предел ≈1 300–1 470 запросов/с: с 1500 итераций/с пропускная способность перестаёт расти, медиана 2,1–2,7 с (очередь в Tomcat/Hikari), HTTP-ошибок нет. k6 упёрся в 3000 VU: 526 тыс. итераций пропущено (это и есть «отказ» по SLA). Узкое место — БД: 10 соединений, mysqld до 6 ядер, 16 тыс. SQL/с. Код k6 99 — критерий p95 нарушен (ожидаемо).
A10: L-05 | B10: Всплеск (spike) | C10: 189.6 | D10: 55548 | E10: 29092 | F10: 292.9 | G10: 1457 | H10: 400 | I10: 0 | J10: 200: 55548 | K10: 6.95 | L10: 0.1 | M10: 5.02 | N10: 15.41 | O10: 18.04 | P10: 53.74 | Q10: 14.1 | R10: 256.8 | S10: 1.4 | T10: 72.4 / 259.8 | U10: 90.5 / 305.2 | V10: 13.9 / 42.1 | W10: 343.9 | X10: 789.8 → 800.3 | Y10: 42 / 0.14 | Z10: 11 | AA10: 3848.5 | AB10: PASS | AC10: Всплеск 10 → 400 VU за 10 с (≈730 запросов/с): без ошибок и без роста p95; после спада задержка вернулась к исходной.
A11: L-06 | B11: Шторм авторизаций | C11: 227 | D11: 9618 | E11: 9618 | F11: 42.4 | G11: 190 | H11: 106 | I11: 0 | J11: 200: 9618; пропущено итераций: 56 | K11: 258.91 | L11: 0.1 | M11: 84.65 | N11: 987.93 | O11: 1049.75 | P11: 1979.85 | Q11: 911.79 | R11: 5.1 | S11: 0 | T11: 306.3 / 957.4 | U11: 3.7 / 10.8 | V11: 23.0 / 65.0 | W11: 344.3 | X11: 801.7 → 819.5 | Y11: 6 / 0.03 | Z11: 11 | AA11: 135 | AB11: PASS | AC11: BCrypt: до 50 входов/с медиана ≈80 мс; на 100 входах/с java ≈8 ядер, медиана 0,9 с (×11). Итоговый p95 988 мс — на грани SLA, на ступени 100/с SLA нарушен (1 050 мс).
A12: L-07 | B12: Пакет заказов сборки (очередь) | C12: 189.7 | D12: 3059 | E12: 60 | F12: 16.1 | G12: 88 | H12: 60 | I12: 0 | J12: 200: 2999, 202: 60 | K12: 16.94 | L12: 0.34 | M12: 10.35 | N12: 35.72 | O12: 157.34 | P12: 311.7 | Q12: 22.89 | R12: 2.6 | S12: 0 | T12: 16.7 / 1232.7 | U12: 11.6 / 924.6 | V12: 1.7 / 14.0 | W12: 341.7 | X12: 819.7 → 822.7 | Y12: 10 / 0.09 | Z12: 11 | AA12: 190.4 | AB12: PASS | AC12: 60 одновременных заказов приняты (p95 277 мс), все 60 собраны без сбоев, последний ждал 189 с: очередь строго последовательная, ≈3,2 с на сборку.
A13: L-08 | B13: Скачивание артефактов | C13: 114.9 | D13: 2256 | E13: 2256 | F13: 19.6 | G13: 37 | H13: 20 | I13: 0 | J13: 200: 2256 | K13: 66.17 | L13: -1258.95 | M13: 63.66 | N13: 103.87 | O13: 234.58 | P13: 417.37 | Q13: 87.42 | R13: 41541 | S13: 361.5 | T13: 85.7 / 355.4 | U13: 3.3 / 11.8 | V13: 13.7 / 28.5 | W13: 351.3 | X13: 822.7 → 831.9 | Y13: 8 / 0.05 | Z13: 11 | AA13: 164.1 | AB13: PASS | AC13: 20 потоков: 361 МБ/с, 41,5 ГБ за 2 мин, p95 104 мс, ошибок нет. Число потоков Tomcat выросло до 150 и дальше держится (норма для пула).
A14: L-09 | B14: Длительная нагрузка (soak) | C14: 879.5 | D14: 23230 | E14: 9582 | F14: 26.4 | G14: 148 | H14: 40 | I14: 0 | J14: 200: 22971, 202: 173, 204: 86 | K14: 9.99 | L14: -1232.71 | M14: 6.51 | N14: 18.65 | O14: 73.41 | P14: 398.91 | Q14: 16.75 | R14: 3336.9 | S14: 3.8 | T14: 11.4 / 483.9 | U14: 10.2 / 356.5 | V14: 2.5 / 23.7 | W14: 354.3 | X14: 831.9 → 838.2 | Y14: 26 / 0.14 | Z14: 11 | AA14: 340.1 | AB14: PASS | AC14: 15 мин, 23 230 запросов, 173 сборки: ни ошибок, ни дрейфа задержки (p95 по третям теста 20,6 → 17,8 → 18,7 мс), ни утечек (heap ≈200 МБ стабильно, RSS +6 МБ).
A15: L-10a | B15: Объём: базовая БД | C15: 171.8 | D15: 8845 | E15: 7200 | F15: 51.5 | G15: 119 | H15: 50 | I15: 0 | J15: 200: 8845 | K15: 4.24 | L15: 0.12 | M15: 3.23 | N15: 9.19 | O15: 10.31 | P15: 17.66 | Q15: 8.5 | R15: 23.1 | S15: 0.1 | T15: 8.1 / 17.0 | U15: 9.6 / 15.0 | V15: 1.8 / 4.3 | W15: 451.9 | X15: 980.6 → 980.7 | Y15: 7 / 0.02 | Z15: 11 | AA15: 649.9 | AB15: PASS | AC15: Эталон: 40 итераций/с на стартовых данных, p95 9 мс.
A16: L-10b | B16: Объём: БД ×100 | C16: 173.1 | D16: 8815 | E16: 7201 | F16: 50.9 | G16: 96 | H16: 50 | I16: 0 | J16: 200: 8815 | K16: 9.44 | L16: 0.12 | M16: 4.9 | N16: 27.71 | O16: 31.82 | P16: 37.67 | Q16: 24.26 | R16: 24.4 | S16: 0.1 | T16: 9.5 / 23.0 | U16: 30.9 / 49.5 | V16: 3.5 / 6.7 | W16: 455 | X16: 981.4 → 981.4 | Y16: 10 / 0.02 | Z16: 11 | AA16: 868.1 | AB16: PASS | AC16: На БД ×100 p95 вырос в 3 раза (9 → 28 мс), в основном из-за списка образов (N+1: 56 SQL на страницу из 12); CPU mysqld ×3. SLA выполняется с запасом.
A18: Проверка критериев (thresholds k6)
A19: ID | B19: Профиль | C19: Метрика | D19: Условие | E19: Результат
A20: L-01 | B20: Дымовой (baseline) | C20: http_req_duration | D20: p(95)<300 | E20: PASS
A21: L-01 | B21: Дымовой (baseline) | C21: http_req_failed | D21: rate<0.01 | E21: PASS
A22: L-02 | B22: Просмотр каталогов (гости) | C22: http_req_failed | D22: rate<0.01 | E22: PASS
A23: L-02 | B23: Просмотр каталогов (гости) | C23: http_req_duration{kind:read} | D23: p(95)<500 | E23: PASS
A24: L-03 | B24: Смешанный продакшен-профиль (целевая нагрузка) | C24: http_req_duration{kind:read} | D24: p(95)<500 | E24: PASS
A25: L-03 | B25: Смешанный продакшен-профиль (целевая нагрузка) | C25: http_req_duration{kind:write} | D25: p(95)<1000 | E25: PASS
A26: L-03 | B26: Смешанный продакшен-профиль (целевая нагрузка) | C26: http_req_failed | D26: rate<0.01 | E26: PASS
A27: L-04 | B27: Стресс (поиск предела) | C27: http_req_failed | D27: rate<0.01 | E27: PASS
A28: L-04 | B28: Стресс (поиск предела) | C28: http_req_duration{kind:read} | D28: p(95)<500 | E28: PASS
A29: L-04b | B29: Стресс до отказа (breakpoint) | C29: http_req_failed | D29: rate<0.01 | E29: PASS
A30: L-04b | B30: Стресс до отказа (breakpoint) | C30: http_req_duration{kind:read} | D30: p(95)<500 | E30: FAIL
... A45: L-10b | B45: Объём: БД ×100 | C45: http_req_failed | D45: rate<0.01 | E45: PASS
A47: Проверки ответов (checks k6): только с неуспешными
A48: ID | B48: Профиль | C48: Проверка | D48: Успешно | E48: Неуспешно | F48: Доля неуспешных

Sheet Нагрузка — эндпоинты
A1: Время отклика по операциям (тег name в k6), мс
A3: ID | B3: Профиль | C3: Операция | D3: Запросов | E3: Ошибок | F3: Avg | G3: Min | H3: Med | I3: p90 | J3: p95 | K3: p99 | L3: Max | M3: % ошибок
A4: L-01 | B4: Дымовой (baseline) | C4: web_asset | D4: 56 | E4: 0 | F4: 2.3 | G4: 1.22 | H4: 1.98 | I4: 2.63 | J4: 4.43 | K4: 8.88 | L4: 9.2 | M4: =IF(D4=0,0,E4/D4) -> 0
A5: L-01 | B5: Дымовой (baseline) | C5: web_page | D5: 28 | E5: 0 | F5: 2.43 | G5: 1.82 | H5: 2.41 | I5: 2.87 | J5: 3.22 | K5: 3.5 | L5: 3.56 | M5: =IF(D5=0,0,E5/D5) -> 0
A6: L-01 | B6: Дымовой (baseline) | C6: components_list | D6: 28 | E6: 0 | F6: 17.33 | G6: 9.8 | H6: 17.62 | I6: 25.88 | J6: 26.78 | K6: 29.27 | L6: 30.13 | M6: =IF(D6=0,0,E6/D6) -> 0
A7: L-01 | B7: Дымовой (baseline) | C7: types | D7: 28 | E7: 0 | F7: 7.36 | G7: 5.46 | H7: 7.04 | I7: 8.95 | J7: 9.37 | K7: 11.34 | L7: 12 | M7: =IF(D7=0,0,E7/D7) -> 0
A8: L-01 | B8: Дымовой (baseline) | C8: auth_login | D8: 28 | E8: 0 | F8: 110.97 | G8: 106.67 | H8: 110.93 | I8: 114 | J8: 117.23 | K8: 118.22 | L8: 118.34 | M8: =IF(D8=0,0,E8/D8) -> 0
A9: L-01 | B9: Дымовой (baseline) | C9: me | D9: 28 | E9: 0 | F9: 14.61 | G9: 10.48 | H9: 14.39 | I9: 17.15 | J9: 18.06 | K9: 21.81 | L9: 23.05 | M9: =IF(D9=0,0,E9/D9) -> 0
A10: L-01 | B10: Дымовой (baseline) | C10: my_images | D10: 28 | E10: 0 | F10: 22.19 | G10: 17.82 | H10: 21.67 | I10: 25.18 | J10: 26.71 | K10: 28.63 | L10: 29.21 | M10: =IF(D10=0,0,E10/D10) -> 0
A11: L-01 | B11: Дымовой (baseline) | C11: admin_users | D11: 28 | E11: 0 | F11: 28.9 | G11: 23.95 | H11: 28.83 | I11: 32.38 | J11: 33.13 | K11: 34.4 | L11: 34.75 | M11: =IF(D11=0,0,E11/D11) -> 0
A12: L-01 | B12: Дымовой (baseline) | C12: images_list | D12: 22 | E12: 0 | F12: 19.18 | G12: 0.76 | H12: 18.13 | I12: 26.96 | J12: 28.49 | K12: 33.75 | L12: 35.13 | M12: =IF(D12=0,0,E12/D12) -> 0
A13: L-01 | B13: Дымовой (baseline) | C13: image_poll | D13: 18 | E13: 0 | F13: 19.16 | G13: 16.06 | H13: 18.73 | I13: 22.26 | J13: 22.45 | K13: 22.47 | L13: 22.47 | M13: =IF(D13=0,0,E13/D13) -> 0
A14: L-01 | B14: Дымовой (baseline) | C14: components_get | D14: 7 | E14: 0 | F14: 9.2 | G14: 7.16 | H14: 9.05 | I14: 11.09 | J14: 12.38 | K14: 13.41 | L14: 13.67 | M14: =IF(D14=0,0,E14/D14) -> 0
A15: L-01 | B15: Дымовой (baseline) | C15: build_order | D15: 6 | E15: 0 | F15: 46.56 | G15: 41.19 | H15: 46.85 | I15: 49.24 | J15: 50.14 | K15: 50.87 | L15: 51.05 | M15: =IF(D15=0,0,E15/D15) -> 0
... A101: L-10b | B101: Объём: БД ×100 | C101: web_page | D101: 344 | E101: 0 | F101: 0.93 | G101: 0.63 | H101: 0.92 | I101: 1.13 | J101: 1.22 | K101: 1.39 | L101: 1.65 | M101: =IF(D101=0,0,E101/D101) -> 0

Sheet Ступени нагрузки
A1: Поведение системы на ступенях нагрузки (плато ступени, без участков разгона)
A3: L-04 Стресс: чтение каталогов
A4: Цель, итераций/с | B4: Достигнуто, /с | C4: Med, мс | D4: p95, мс | E4: p99, мс | F4: Ошибки | G4: CPU java, %
A5: 50 | B5: 64.6 | C5: 5.5 | D5: 16.2 | E5: 17.4 | F5: 0 | G5: 18
A6: 100 | B6: 131.2 | C6: 5.3 | D6: 15.8 | E6: 16.8 | F6: 0 | G6: 33
A7: 200 | B7: 258 | C7: 4.9 | D7: 15.4 | E7: 16.6 | F7: 0 | G7: 64
A8: 300 | B8: 402.9 | C8: 5 | D8: 15.5 | E8: 16.5 | F8: 0 | G8: 100
A9: 450 | B9: 606.2 | C9: 4.6 | D9: 14.9 | E9: 16.1 | F9: 0 | G9: 141
A10: 600 | B10: 755.2 | C10: 3.9 | D10: 12.4 | E10: 13.8 | F10: 0 | G10: 150
A21: L-04b Стресс до отказа
A22: Цель, итераций/с | B22: Достигнуто, /с | C22: Med, мс | D22: p95, мс | E22: p99, мс | F22: Ошибки | G22: CPU java, %
A23: 1000 | B23: 1283.6 | C23: 3.8 | D23: 11.7 | E23: 13.7 | F23: 0 | G23: 225
A24: 1500 | B24: 1168.5 | C24: 2732.2 | D24: 3101.4 | E24: 3301.6 | F24: 0 | G24: 350
A25: 2000 | B25: 1213.4 | C25: 2692 | D25: 3047.3 | E25: 3241.4 | F25: 0 | G25: 353
A26: 3000 | B26: 1403.8 | C26: 2275.8 | D26: 2648.9 | E26: 2859.2 | F26: 0 | G26: 355
A27: 4000 | B27: 1468.1 | C27: 2138.2 | D27: 2496.4 | E27: 2662.8 | F27: 0 | G27: 372
A39: L-06 Шторм авторизаций
A40: Цель, входов/с | B40: Достигнуто, /с | C40: Med, мс | D40: p95, мс | E40: p99, мс | F40: Ошибки | G40: CPU java, %
A41: 10 | B41: 10.6 | C41: 91.1 | D41: 96.8 | E41: 99.2 | F41: 0 | G41: 78
A42: 25 | B42: 27 | C42: 80 | D42: 86.4 | E42: 88.6 | F42: 0 | G42: 179
A43: 50 | B43: 55.2 | C43: 81.6 | D43: 86.6 | E43: 90 | F43: 0 | G43: 373
A44: 100 | B44: 100.7 | C44: 912.3 | D44: 1049.6 | E44: 1076.7 | F44: 0 | G44: 776
A57: L-05 Всплеск
A58: Фаза | B58: Достигнуто, /с | C58: Med, мс | D58: p95, мс | E58: p99, мс | F58: Ошибки | G58: CPU java, %
A59: 10 VU (до всплеска) | B59: 36.7 | C59: 5.4 | D59: 16.8 | E59: 18.5 | F59: 0 | G59: 10
A60: 400 VU (всплеск) | B60: 731 | C60: 5 | D60: 15.2 | E60: 17.9 | F60: 0 | G60: 189
A61: 10 VU (после) | B61: 19 | C61: 6.4 | D61: 17.4 | E61: 18.4 | F61: 0 | G61: 7

Sheet Временные ряды
A1: Временные ряды (шаг 5 с): нагрузка, отклик, ресурсы
A2: Графики — справа от каждого блока
A3: L-01 Дымовой (baseline)
A4: t, с | B4: VU | C4: RPS | D4: p95, мс | E4: Avg, мс | F4: Ошибки, % | G4: CPU java, % | H4: CPU mysqld, % | I4: CPU машины, % | J4: Heap, МБ | K4: Соед. БД
A5: 0 | B5: 1 | C5: 2.8 | D5: 70.3 | E5: 27.9 | F5: 0 | G5: 25.3 | H5: 4.2 | I5: 3.4 | J5: 40.5 | K5: 11
A6: 5 | B6: 1 | C6: 7.6 | D6: 112.1 | E6: 30.3 | F6: 0 | G6: 21.2 | H6: 3.3 | I6: 2.6 | J6: 51.9 | K6: 11
A7: 10 | B7: 1 | C7: 3.4 | D7: 110.4 | E7: 28 | F7: 0 | G7: 11.7 | H7: 2.8 | I7: 1.6 | J7: 68.7 | K7: 11
A8: 15 | B8: 1 | C8: 8.8 | D8: 112.5 | E8: 27.3 | F8: 0 | G8: 18 | H8: 1.6 | I8: 3.2 | J8: 82.9 | K8: 11
A9: 20 | B9: 1 | C9: 3.2 | D9: 134.7 | E9: 34.3 | F9: 0 | G9: 25.8 | H9: 3.5 | I9: 2.6 | J9: 100.5 | K9: 11
A10: 25 | B10: 1 | C10: 8.4 | D10: 111.4 | E10: 21.6 | F10: 0 | G10: 33.2 | H10: 3.5 | I10: 2.7 | J10: 111.1 | K10: 11
A11: 30 | B11: 1 | C11: 2.8 | D11: 64.7 | E11: 22.6 | F11: 0 | G11: 9.2 | H11: 3.4 | I11: 1.2 | J11: 125.9 | K11: 11
A12: 35 | B12: 1 | C12: 8.4 | D12: 111.8 | E12: 25 | F12: 0 | G12: 29.3 | H12: 3.9 | I12: 2.4 | J12: 138.9 | K12: 11
A13: 40 | B13: 1 | C13: 3 | D13: 65.7 | E13: 23.3 | F13: 0 | G13: 15.7 | H13: 3.1 | I13: 1.6 | J13: 155.5 | K13: 11
A14: 45 | B14: 1 | C14: 9.8 | D14: 108.2 | E14: 23.6 | F14: 0 | G14: 22 | H14: 2.2 | I14: 2.4 | J14: 167.9 | K14: 11
A15: 50 | B15: 1 | C15: 1.8 | D15: 109.7 | E15: 42.2 | F15: 0 | G15: 13.5 | H15: 3.3 | I15: 1.6 | J15: 184.9 | K15: 11
A16: 55 | B16: 1 | C16: 4 | D16: 107.2 | E16: 22 | F16: 0 | G16: 28.4 | H16: 4.9 | I16: 2.6 | J16: 190.9 | K16: 11
A20: L-02 Просмотр каталогов (гости)
A21: t, с | B21: VU | C21: RPS | D21: p95, мс | E21: Avg, мс | F21: Ошибки, % | G21: CPU java, % | H21: CPU mysqld, % | I21: CPU машины, % | J21: Heap, МБ | K21: Соед. БД
A22: 0 | B22: 3 | C22: 4 | D22: 14.8 | E22: 6.1 | F22: 0 | G22: 2.1 | H22: 2.5 | I22: 0.6 | J22: 311.8 | K22: 11
A23: 5 | B23: 9 | C23: 11.2 | D23: 16 | E23: 7 | F23: 0 | G23: 6.2 | H23: 2.5 | I23: 1.2 | J23: 220.8 | K23: 11
A24: 10 | B24: 13 | C24: 13.2 | D24: 13.1 | E24: 6.3 | F24: 0 | G24: 8.6 | H24: 3.9 | I24: 1.3 | J24: 39.5 | K24: 11
A25: 15 | B25: 18 | C25: 11.8 | D25: 14.5 | E25: 6.9 | F25: 0 | G25: 10.6 | H25: 4.9 | I25: 1.5 | J25: 51.1 | K25: 11
A26: 20 | B26: 22 | C26: 15.6 | D26: 16.8 | E26: 7.7 | F26: 0 | G26: 13.9 | H26: 6.5 | I26: 1.8 | J26: 65.3 | K26: 11
A27: 25 | B27: 26 | C27: 20 | D27: 15.3 | E27: 7.3 | F27: 0 | G27: 11.6 | H27: 7.3 | I27: 1.6 | J27: 81.3 | K27: 11
A28: 30 | B28: 30 | C28: 21.4 | D28: 15.7 | E28: 7.1 | F28: 0 | G28: 15.3 | H28: 7.5 | I28: 1.9 | J28: 100.9 | K28: 11
A29: 35 | B29: 36 | C29: 33 | D29: 15.1 | E29: 7.2 | F29: 0 | G29: 5.3 | H29: 3.4 | I29: 3.1 | J29: 123.5 | K29: 11
A30: 40 | B30: 40 | C30: 31.2 | D30: 14.9 | E30: 7.1 | F30: 0 | G30: 26.7 | H30: 9.8 | I30: 2.8 | J30: 151.1 | K30: 11
A31: 45 | B31: 44 | C31: 31 | D31: 15.7 | E31: 7.2 | F31: 0 | G31: 37.1 | H31: 10.8 | I31: 3.7 | J31: 179.7 | K31: 11
A32: 50 | B32: 48 | C32: 33.8 | D32: 15.3 | E32: 7.2 | F32: 0 | G32: 12.6 | H32: 12 | I32: 2 | J32: 210.5 | K32: 11
A33: 55 | B33: 50 | C33: 32.8 | D33: 15 | E33: 7.5 | F33: 0 | G33: 11.7 | H33: 12.1 | I33: 1.9 | J33: 243.5 | K33: 11
... A73: 255 | B73: 1 | C73: 0.2 | D73: 5.9 | E73: 5.9 | F73: 0 | G73: 0.7 | H73: 1.7 | I73: 0.3 | J73: 117.3 | K73: 11
A76: L-03 Смешанный продакшен-профиль (целевая нагрузка)
A77: t, с | B77: VU | C77: RPS | D77: p95, мс | E77: Avg, мс | F77: Ошибки, % | G77: CPU java, % | H77: CPU mysqld, % | I77: CPU машины, % | J77: Heap, МБ | K77: Соед. БД
A78: 0 | B78: 7 | C78: 7.2 | D78: 48.7 | E78: 13.3 | F78: 0 | G78: 28.6 | H78: 4.9 | I78: 2.5 | J78: 138.9 | K78: 11
A79: 5 | B79: 16 | C79: 12.2 | D79: 57.3 | E79: 13.8 | F79: 0 | G79: 33.6 | H79: 5.3 | I79: 3 | J79: 152.9 | K79: 11
A80: 10 | B80: 23 | C80: 17.6 | D80: 30.1 | E80: 10.4 | F80: 0 | G80: 45.1 | H80: 7.4 | I80: 4.2 | J80: 174.9 | K80: 11
A81: 15 | B81: 32 | C81: 23.6 | D81: 21.4 | E81: 12.7 | F81: 0 | G81: 28.6 | H81: 8.6 | I81: 3.7 | J81: 210.3 | K81: 11
A82: 20 | B82: 41 | C82: 27.4 | D82: 31.9 | E82: 12.6 | F82: 0 | G82: 23.4 | H82: 11.6 | I82: 3.4 | J82: 246.5 | K82: 11
A83: 25 | B83: 48 | C83: 36.8 | D83: 19.4 | E83: 9.9 | F83: 0 | G83: 23.2 | H83: 13.6 | I83: 3.9 | J83: 297.9 | K83: 11
A84: 30 | B84: 58 | C84: 54.4 | D84: 18.9 | E84: 10.1 | F84: 0 | G84: 25.7 | H84: 9.4 | I84: 3.7 | J84: 71.2 | K84: 11
A85: 35 | B85: 66 | C85: 44.6 | D85: 18.1 | E85: 9.7 | F85: 0 | G85: 29.2 | H85: 16.7 | I85: 4.2 | J85: 140 | K85: 11
A86: 40 | B86: 75 | C86: 49.6 | D86: 18.5 | E86: 10.5 | F86: 0 | G86: 37.5 | H86: 18.3 | I86: 5.1 | J86: 211.2 | K86: 11
A87: 45 | B87: 82 | C87: 56.2 | D87: 24.7 | E87: 10.8 | F87: 0 | G87: 42.9 | H87: 21.4 | I87: 5.7 | J87: 231.5 | K87: 11
A88: 50 | B88: 91 | C88: 61.2 | D88: 17.9 | E88: 9.7 | F88: 0 | G88: 36.1 | H88: 23 | I88: 5.6 | J88: 85.7 | K88: 11
A89: 55 | B89: 100 | C89: 68 | D89: 16.1 | E89: 8.9 | F89: 0 | G89: 51.9 | H89: 22.2 | I89: 5.9 | J89: 182.1 | K89: 11
... A152: 370 | B152: 16 | C152: 2.4 | D152: 162.3 | E152: 36.2 | F152: 0 | G152: 7.1 | H152: 3.4 | I152: 1.7 | J152: 169.9 | K152: 11
A155: L-04 Стресс (поиск предела)
A156: t, с | B156: VU | C156: RPS | D156: p95, мс | E156: Avg, мс | F156: Ошибки, % | G156: CPU java, % | H156: CPU mysqld, % | I156: CPU машины, % | J156: Heap, МБ | K156: Соед. БД
A157: 0 | B157: 1 | C157: 27.4 | D157: 18.4 | E157: 8.8 | F157: 0 | G157: 17 | H157: 15.6 | I157: 3.8 | J157: 201.9 | K157: 11
A158: 5 | B158: 1 | C158: 37.8 | D158: 18 | E158: 8.2 | F158: 0 | G158: 14.3 | H158: 14.7 | I158: 2.6 | J158: 242.1 | K158: 11
A159: 10 | B159: 0 | C159: 40.8 | D159: 18.1 | E159: 8.6 | F159: 0 | G159: 16.1 | H159: 17.1 | I159: 2.9 | J159: 282.7 | K159: 11
A160: 15 | B160: 1 | C160: 50.2 | D160: 17.5 | E160: 8.2 | F160: 0 | G160: 20.1 | H160: 19.6 | I160: 3 | J160: 181.4 | K160: 11
A161: 20 | B161: 1 | C161: 55 | D161: 16.8 | E161: 7.9 | F161: 0 | G161: 11 | H161: 11.7 | I161: 3.3 | J161: 96.9 | K161: 11
A162: 25 | B162: 1 | C162: 78.2 | D162: 16.2 | E162: 7.7 | F162: 0 | G162: 19.2 | H162: 21.9 | I162: 3.4 | J162: 169.2 | K162: 11
A163: 30 | B163: 1 | C163: 61 | D163: 16.2 | E163: 7.4 | F163: 0 | G163: 20.5 | H163: 22 | I163: 3.8 | J163: 241.9 | K163: 11
A164: 35 | B164: 1 | C164: 61.2 | D164: 16.4 | E164: 7.5 | F164: 0 | G164: 20.3 | H164: 22.4 | I164: 3.9 | J164: 305.7 | K164: 11
A165: 40 | B165: 1 | C165: 61.8 | D165: 16.9 | E165: 7.5 | F165: 0 | G165: 20.4 | H165: 23 | I165: 3.8 | J165: 70.6 | K165: 11
A166: 45 | B166: 1 | C166: 64.8 | D166: 16 | E166: 7.5 | F166: 0 | G166: 19.9 | H166: 23.6 | I166: 3.7 | J166: 138 | K166: 11
A167: 50 | B167: 1 | C167: 60.2 | D167: 16.2 | E167: 7.4 | F167: 0 | G167: 19.2 | H167: 22.2 | I167: 3.5 | J167: 197.6 | K167: 11
A168: 55 | B168: 1 | C168: 80.8 | D168: 16.3 | E168: 7.3 | F168: 0 | G168: 11.9 | H168: 13.3 | I168: 3.4 | J168: 267.5 | K168: 11
... A259: 510 | B259: 4 | C259: 632.6 | D259: 12.5 | E259: 5.5 | F259: 0 | G259: 139.1 | H259: 172.3 | I259: 24.6 | J259: 176.7 | K259: 11
A262: L-04b Стресс до отказа (breakpoint)
A263: t, с | B263: VU | C263: RPS | D263: p95, мс | E263: Avg, мс | F263: Ошибки, % | G263: CPU java, % | H263: CPU mysqld, % | I263: CPU машины, % | J263: Heap, МБ | K263: Соед. БД
A264: 0 | B264: 8 | C264: 692.6 | D264: 16.7 | E264: 7.5 | F264: 0 | G264: 214.1 | H264: 276.4 | I264: 42.2 | J264: 208.8 | K264: 11
A265: 5 | B265: 10 | C265: 844.2 | D265: 15.9 | E265: 7 | F265: 0 | G265: 241.8 | H265: 319 | I265: 43.6 | J265: 177.4 | K265: 11
A266: 10 | B266: 5 | C266: 927.8 | D266: 12 | E266: 5.4 | F266: 0 | G266: 203.4 | H266: 265.3 | I266: 36.2 | J266: 170.5 | K266: 11
A267: 15 | B267: 9 | C267: 1315.2 | D267: 11.7 | E267: 5.2 | F267: 0 | G267: 88.6 | H267: 118 | I267: 38.5 | J267: 179.2 | K267: 11
A268: 20 | B268: 7 | C268: 1113.6 | D268: 11.7 | E268: 5.2 | F268: 0 | G268: 236.3 | H268: 309 | I268: 42.5 | J268: 247.2 | K268: 11
A269: 25 | B269: 8 | C269: 1201.8 | D269: 11.9 | E269: 5.2 | F269: 0 | G269: 247.7 | H269: 327 | I269: 45.6 | J269: 177.1 | K269: 11
A270: 30 | B270: 11 | C270: 1228.4 | D270: 11.8 | E270: 5.2 | F270: 0 | G270: 253.7 | H270: 335 | I270: 46.2 | J270: 236.2 | K270: 11
A271: 35 | B271: 8 | C271: 1222.2 | D271: 11.5 | E271: 5.1 | F271: 0 | G271: 252.9 | H271: 331.7 | I271: 45.1 | J271: 199.9 | K271: 11
A272: 40 | B272: 9 | C272: 1214.2 | D272: 11.8 | E272: 5.2 | F272: 0 | G272: 255.8 | H272: 335 | I272: 46.5 | J272: 185.7 | K272: 11
A273: 45 | B273: 10 | C273: 1531 | D273: 11.6 | E273: 5.1 | F273: 0 | G273: 103.8 | H273: 138.7 | I273: 45.3 | J273: 225.2 | K273: 11
A274: 50 | B274: 10 | C274: 1257 | D274: 11.5 | E274: 5 | F274: 0 | G274: 251.3 | H274: 330.2 | I274: 44.6 | J274: 252.2 | K274: 11
A275: 55 | B275: 9 | C275: 1222.6 | D275: 12 | E275: 5.4 | F275: 0 | G275: 257.2 | H275: 339.4 | I275: 47.7 | J275: 175 | K275: 11
... A350: 430 | B350: 3000 | C350: 1110.8 | D350: 2312.6 | E350: 1947.2 | F350: 0 | G350: 398.3 | H350: 539.6 | I350: 71.7 | J350: 292.6 | K350: 11
A353: L-05 Всплеск (spike)
A354: t, с | B354: VU | C354: RPS | D354: p95, мс | E354: Avg, мс | F354: Ошибки, % | G354: CPU java, % | H354: CPU mysqld, % | I354: CPU машины, % | J354: Heap, МБ | K354: Соед. БД
A355: 0 | B355: 10 | C355: 25.4 | D355: 16.9 | E355: 8.4 | F355: 0 | G355: 10.3 | H355: 10.4 | I355: 3.4 | J355: 227.4 | K355: 11
A356: 5 | B356: 10 | C356: 22.8 | D356: 17.6 | E356: 8.3 | F356: 0 | G356: 4.4 | H356: 5.8 | I356: 1.9 | J356: 253.1 | K356: 11
A357: 10 | B357: 10 | C357: 21.8 | D357: 17.7 | E357: 8.4 | F357: 0 | G357: 7.3 | H357: 9 | I357: 1.5 | J357: 277 | K357: 11
A358: 15 | B358: 10 | C358: 19.2 | D358: 16.3 | E358: 8 | F358: 0 | G358: 7.3 | H358: 8.8 | I358: 1.5 | J358: 300.8 | K358: 11
A359: 20 | B359: 10 | C359: 17.8 | D359: 16.8 | E359: 7.7 | F359: 0 | G359: 6.7 | H359: 8.2 | I359: 1.4 | J359: 325.2 | K359: 11
A360: 25 | B360: 10 | C360: 17.2 | D360: 16.9 | E360: 8.5 | F360: 0 | G360: 6.5 | H360: 7.6 | I360: 1.3 | J360: 100.6 | K360: 11
A361: 30 | B361: 10 | C361: 17 | D361: 16.5 | E361: 8.5 | F361: 0 | G361: 7.1 | H361: 8.4 | I361: 1.5 | J361: 61.1 | K361: 11
A362: 35 | B362: 10 | C362: 23.4 | D362: 17.9 | E362: 8.3 | F362: 0 | G362: 4.5 | H362: 5.8 | I362: 1.7 | J362: 85.8 | K362: 11
A363: 40 | B363: 10 | C363: 22 | D363: 16.9 | E363: 8.3 | F363: 0 | G363: 6.7 | H363: 8.3 | I363: 1.2 | J363: 110.9 | K363: 11
A364: 45 | B364: 10 | C364: 21 | D364: 16.9 | E364: 8.7 | F364: 0 | G364: 8.3 | H364: 10.4 | I364: 1.6 | J364: 135.5 | K364: 11
A365: 50 | B365: 10 | C365: 17.2 | D365: 17.1 | E365: 9.3 | F365: 0 | G365: 7.5 | H365: 9 | I365: 1.4 | J365: 159.1 | K365: 11
A366: 55 | B366: 113 | C366: 190 | D366: 16.2 | E366: 5.7 | F366: 0 | G366: 35.2 | H366: 42.5 | I366: 7.5 | J366: 204.5 | K366: 11
... A392: 185 | B392: 10 | C392: 18.2 | D392: 17.4 | E392: 8.8 | F392: 0 | G392: 8.3 | H392: 9.1 | I392: 1.6 | J392: 280.2 | K392: 11
A395: L-06 Шторм авторизаций
A396: t, с | B396: VU | C396: RPS | D396: p95, мс | E396: Avg, мс | F396: Ошибки, % | G396: CPU java, % | H396: CPU mysqld, % | I396: CPU машины, % | J396: Heap, МБ | K396: Соед. БД
A397: 0 | B397: 1 | C397: 5 | D397: 109.7 | E397: 100.7 | F397: 0 | G397: 31.5 | H397: 1.4 | I397: 4.3 | J397: 85.7 | K397: 11
A398: 5 | B398: 1 | C398: 7.8 | D398: 107.3 | E398: 104.7 | F398: 0 | G398: 63.3 | H398: 2.4 | I398: 4.7 | J398: 94 | K398: 11
A399: 10 | B399: 1 | C399: 7.2 | D399: 110.3 | E399: 105.5 | F399: 0 | G399: 72.2 | H399: 2.6 | I399: 5.3 | J399: 104.2 | K399: 11
A400: 15 | B400: 1 | C400: 8.2 | D400: 105.6 | E400: 103.7 | F400: 0 | G400: 80.1 | H400: 2.4 | I400: 5.8 | J400: 112.4 | K400: 11
A401: 20 | B401: 1 | C401: 8.8 | D401: 109.1 | E401: 105.1 | F401: 0 | G401: 91.2 | H401: 2.5 | I401: 6.5 | J401: 122.6 | K401: 11
A402: 25 | B402: 1 | C402: 9.8 | D402: 107.7 | E402: 93.7 | F402: 0 | G402: 86.3 | H402: 2.4 | I402: 6.4 | J402: 133.8 | K402: 11
A403: 30 | B403: 1 | C403: 10 | D403: 97.9 | E403: 90.3 | F403: 0 | G403: 84 | H403: 2.4 | I403: 5.9 | J403: 145 | K403: 11
...

Sheet Объёмный тест
A1: Объёмный тест: запросы каталога на стартовой БД и на БД ×100
A2: Одиночные запросы без конкурентной нагрузки, 30 повторов (tests/load/heavy_queries.py); SQL — число запросов к MySQL на один HTTP-запрос.
A4: Запрос | B4: Записей (база) | C4: Записей (×100) | D4: SQL (база) | E4: SQL (×100) | F4: Med база, мс | G4: Med ×100, мс | H4: p95 база, мс | I4: p95 ×100, мс | J4: Рост p95, раз
A5: Образы: первая страница (12) | B5: 388 | C5: 20388 | D5: 28 | E5: 56 | F5: 9.6 | G5: 16.7 | H5: 10.5 | I5: 17.9 | J5: =IF(H5=0,0,I5/H5) -> 1.7047619
A6: Образы: страница 100 макс. размера | B6: 388 | C6: 20388 | D6: 116 | E6: 389 | F6: 35.8 | G6: 89.6 | H6: 44.2 | I6: 102.8 | J6: =IF(H6=0,0,I6/H6) -> 2.3257919
A7: Образы: глубокая страница (page=1500) | B7: 388 | C7: 20388 | D7: 9 | E7: 57 | F7: 3.4 | G7: 25.6 | H7: 3.9 | I7: 26.9 | J7: =IF(H7=0,0,I7/H7) -> 6.8974359
A8: Образы: поиск по подстроке | B8: 0 | C8: 111 | D8: 8 | E8: 56 | F8: 2.5 | G8: 25.7 | H8: 3.1 | I8: 32.8 | J8: =IF(H8=0,0,I8/H8) -> 10.580645
A9: Образы: фильтр по 2 компонентам | B9: 134 | C9: 134 | D9: 28 | E9: 28 | F9: 9.5 | G9: 9.9 | H9: 10.4 | I9: 10.4 | J9: =IF(H9=0,0,I9/H9) -> 1
A10: Образы: сортировка по цене ↓ + статус | B10: 387 | C10: 18387 | D10: 27 | E10: 57 | F10: 8.8 | G10: 33.6 | H10: 9.6 | I10: 35.7 | J10: =IF(H10=0,0,I10/H10) -> 3.71875
A11: Компоненты: первая страница | B11: 71 | C11: 2071 | D11: 23 | E11: 23 | F11: 6.1 | G11: 6.8 | H11: 6.7 | I11: 7.4 | J11: =IF(H11=0,0,I11/H11) -> 1.1044776
A12: Компоненты: поиск + тип + цена ↑ | B12: 0 | C12: 555 | D12: 8 | E12: 22 | F12: 2.3 | G12: 8 | H12: 2.6 | I12: 10.4 | J12: =IF(H12=0,0,I12/H12) -> 4
A13: Пользователи (ADMIN): поиск | B13: 0 | C13: 1111 | D13: 10 | E13: 31 | F13: 4.2 | G13: 13 | H13: 5 | I13: 14.8 | J13: =IF(H13=0,0,I13/H13) -> 2.96
A16: Под нагрузкой 40 запросов/с, 3 мин (профили L-10a и L-10b)
A17: Показатель | B17: Стартовая БД | C17: БД ×100 | D17: Изменение
A18: Средняя задержка, мс | B18: 4.24 | C18: 9.44 | D18: =IF(OR(B18="",B18=0),"—",C18/B18) -> 2.2264151
A19: Медиана, мс | B19: 3.23 | C19: 4.9 | D19: =IF(OR(B19="",B19=0),"—",C19/B19) -> 1.5170279
A20: p95, мс | B20: 9.19 | C20: 27.71 | D20: =IF(OR(B20="",B20=0),"—",C20/B20) -> 3.0152339
A21: p99, мс | B21: 10.31 | C21: 31.82 | D21: =IF(OR(B21="",B21=0),"—",C21/B21) -> 3.086324
A22: Ошибки, % | B22: 0 | C22: 0 | D22: =IF(OR(B22="",B22=0),"—",C22/B22) -> —
A23: CPU java, средн. % | B23: 8.1 | C23: 9.5 | D23: =IF(OR(B23="",B23=0),"—",C23/B23) -> 1.1728395
A24: CPU mysqld, средн. % | B24: 9.6 | C24: 30.9 | D24: =IF(OR(B24="",B24=0),"—",C24/B24) -> 3.21875
A25: SQL-запросов/с | B25: 649.9 | C25: 868.1 | D25: =IF(OR(B25="",B25=0),"—",C25/B25) -> 1.335744
A27: • Наполнение (tests/load/volume_seed.sql, 8 с): 20 388 образов (90 % READY), 2 071 компонент, 61 017 связей образ–компонент, 5 190 пользователей.
A28: • Число SQL на страницу растёт с числом компонентов в образах (N+1): первая страница — 28 → 56 запросов, страница из 100 образов — 389 запросов (90 мс).
A29: • Глубокая пагинация (OFFSET 18 000) замедлилась в 7,5 раза; сортировка по цене со статусом — filesort по 18 тыс. строк (34 мс); индексов по name/state/cost нет (DEF-23).
A30: • Под нагрузкой 40 итераций/с p95 вырос в 3 раза (9 → 28 мс), CPU mysqld — тоже в 3 раза. Запас по SLA сохраняется, но задержка растёт линейно с объёмом данных.

Sheet Очередь сборок
A1: Очередь сборок под нагрузкой
A2: Сборка в режиме симуляции с задержкой LUCKFOX_SIM_DELAY=3 с (+ mkfs.ext4); время до READY измеряется от ответа на заказ до статуса READY.
A4: Профиль | B4: Готово | C4: Сбоев | D4: Avg, с | E4: Min, с | F4: Med, с | G4: p90, с | H4: p95, с | I4: Max, с | J4: Пропускн., сборок/мин
A5: L-01 Дымовой (baseline) | B5: 6 | C5: 0 | D5: 4.06 | E5: 4.05 | F5: 4.06 | G5: 4.07 | H5: 4.07 | I5: 4.07 | J5: 6.4
A6: L-03 Смешанный продакшен-профиль (целевая нагрузка) | B6: 116 | C6: 0 | D6: 12.54 | E6: 4.03 | F6: 14.08 | G6: 16.08 | H6: 16.1 | I6: 18.11 | J6: 18.6
A7: L-07 Пакет заказов сборки (очередь) | B7: 60 | C7: 0 | D7: 98.09 | E7: 4.16 | F7: 98.76 | G7: 171.19 | H7: 181.11 | I7: 189.47 | J7: 19
A8: L-09 Длительная нагрузка (soak) | B8: 173 | C8: 0 | D8: 4.41 | E8: 2.31 | F8: 4.03 | G8: 6.04 | H8: 6.32 | I8: 10.06 | J8: 11.8
A10: • Очередь выполняет строго одну сборку за раз (INT-36, L-07): 60 одновременных заказов обработаны за ≈190 с, последний ждал 189 с, потерь и сбоев нет.
A11: • В смешанном профиле (8 заказчиков) среднее время до READY — 12,5 с при чистой сборке ≈3,2 с: ожидание в очереди в 3–4 раза дольше самой сборки.
A12: • Экстраполяция на реальную сборку SDK (1–3 ч): 8–24 образа в сутки; очередь из 60 заказов — 2,5–7,5 суток ожидания (DEF-24).
A13: • Все нагрузочные тесты в БД провисел образ #33 в статусе BUILDING, оставшийся после аварийного перезапуска в INT-45: очередь его так и не подхватила (DEF-19).
